Workbook

Sheet MUESTREO
B3: EMPRESA | C3: DEPARTAMENTO | D3: CARGO | E3: EVALUADO | F3: FECHA | G3: DEPARTAMENTO SOPORTE | H3: CARGO SOPORTE | I3: ACTIVIDAD | J3: PROCESO | K3: ACCIONES | L3: TIPO DE ANALISIS | M3: DEPARTAMENTO ENC | N3: TIEMPO INICIO | O3: TIEMPO FIN | P3: TIEMPO | Q3: OBSERVACIONES | R3: OPORTUNIDADES DE MEJORA
B4: TSER | C4: CONTABILIDAD | D4: ANALISTA CONTABLE 2 EXPORTADORAS | E4: GERALDINE NAULA | F4: 45971 | I4: CONSOLIDACIÓN DE VENTAS CÍAS RELACIONADAS A MLC | J4: =IFERROR(VLOOKUP(MUESTREO_LABORAL_A2[[#This Row],[ACTIVIDAD]],'Lista Maestra'!$D$6:$F$190,3,0),"") -> CONCILIACIÓN DE VENTAS Y COMPRAS ENTRE RELACIONADAS | K4: =IFERROR(VLOOKUP(MUESTREO_LABORAL_A2[[#This Row],[ACTIVIDAD]],'Lista Maestra'!$D$6:$F$190,2,0),"") -> REALIZACIÓN Y ANÁLISIS DE CONCILIACIONES DE VENTAS ENTRE EXPORTADORAS RELACIONADAS PARA VERIFICAR QUE LOS REGISTROS DE VENTAS ESTÉN CUADRADOS, IDENTIFICANDO DIFERENCIAS Y REGISTRANDO AJUSTES CONTABLES NECESARIOS. | L4: CON ACTIVIDAD | N4: 0.35416667 | O4: 0.36805556 | P4: =IF(MUESTREO_LABORAL_A2[[#This Row],[TIEMPO INICIO]]="","",(MUESTREO_LABORAL_A2[[#This Row],[TIEMPO FIN]]-MUESTREO_LABORAL_A2[[#This Row],[TIEMPO INICIO]])*24) -> 0.33333333 | Q4: Viernes 07/11/2025 envió la conciliación de las exportadoras, comparativo de compras y ventas de compañías relacionadas, vale contra TFE, multi, y TSER. Actualización de la actividad realizada el día viernes 07/11/2025.
B5: TSER | C5: CONTABILIDAD | D5: ANALISTA CONTABLE 2 EXPORTADORAS | E5: GERALDINE NAULA | F5: 45971 | I5: FACTURACIÓN CIF BANANO A CLIENTES EN MULTINATIONAL | J5: =IFERROR(VLOOKUP(MUESTREO_LABORAL_A2[[#This Row],[ACTIVIDAD]],'Lista Maestra'!$D$6:$F$190,3,0),"") -> FACTURACIÓN A CLIENTES | K5: =IFERROR(VLOOKUP(MUESTREO_LABORAL_A2[[#This Row],[ACTIVIDAD]],'Lista Maestra'!$D$6:$F$190,2,0),"") -> ELABORACIÓN SEMANAL DE FACTURAS DE BANANO PARA CLIENTES INTERNACIONALES EN MULTINATIONAL, TRABAJANDO CON LOS REPORTES DE TRÁMITES DE LA SEMANA, DETALLE DE CONSOLIDACIÓN EN FTL Y B/LS CON CIERRE SEMANAL CORRESPONDIENTE. | L5: CON ACTIVIDAD | N5: 0.36805556 | O5: 0.38958333 | P5: =IF(MUESTREO_LABORAL_A2[[#This Row],[TIEMPO INICIO]]="","",(MUESTREO_LABORAL_A2[[#This Row],[TIEMPO FIN]]-MUESTREO_LABORAL_A2[[#This Row],[TIEMPO INICIO]])*24) -> 0.51666667 | Q5: Facturación se refiere al ingreso de facturas en base a una compra de producto. Va a hablar con Jennifer algún cambio de precio o si han habido ciertas divisiones.
B6: TSER | C6: CONTABILIDAD | D6: ANALISTA CONTABLE 2 EXPORTADORAS | E6: GERALDINE NAULA | F6: 45971 | I6: NECESIDADES BIOLÓGICAS | J6: =IFERROR(VLOOKUP(MUESTREO_LABORAL_A2[[#This Row],[ACTIVIDAD]],'Lista Maestra'!$D$6:$F$190,3,0),"") -> NECESIDADES BIOLÓGICAS | K6: =IFERROR(VLOOKUP(MUESTREO_LABORAL_A2[[#This Row],[ACTIVIDAD]],'Lista Maestra'!$D$6:$F$190,2,0),"") -> PROCESO DE MICCIÓN Y AGREGADOS | L6: SA | N6: 0.38958333 | O6: 0.39513889 | P6: =IF(MUESTREO_LABORAL_A2[[#This Row],[TIEMPO INICIO]]="","",(MUESTREO_LABORAL_A2[[#This Row],[TIEMPO FIN]]-MUESTREO_LABORAL_A2[[#This Row],[TIEMPO INICIO]])*24) -> 0.13333333
B7: TSER | C7: CONTABILIDAD | D7: ANALISTA CONTABLE 2 EXPORTADORAS | E7: GERALDINE NAULA | F7: 45971 | I7: FACTURACIÓN CIF BANANO A CLIENTES EN MULTINATIONAL | J7: =IFERROR(VLOOKUP(MUESTREO_LABORAL_A2[[#This Row],[ACTIVIDAD]],'Lista Maestra'!$D$6:$F$190,3,0),"") -> FACTURACIÓN A CLIENTES | K7: =IFERROR(VLOOKUP(MUESTREO_LABORAL_A2[[#This Row],[ACTIVIDAD]],'Lista Maestra'!$D$6:$F$190,2,0),"") -> ELABORACIÓN SEMANAL DE FACTURAS DE BANANO PARA CLIENTES INTERNACIONALES EN MULTINATIONAL, TRABAJANDO CON LOS REPORTES DE TRÁMITES DE LA SEMANA, DETALLE DE CONSOLIDACIÓN EN FTL Y B/LS CON CIERRE SEMANAL CORRESPONDIENTE. | L7: CON ACTIVIDAD | N7: 0.39513889 | O7: 0.41041667 | P7: =IF(MUESTREO_LABORAL_A2[[#This Row],[TIEMPO INICIO]]="","",(MUESTREO_LABORAL_A2[[#This Row],[TIEMPO FIN]]-MUESTREO_LABORAL_A2[[#This Row],[TIEMPO INICIO]])*24) -> 0.36666667 | Q7: Tuvo toda la información lista hasta que Jennifer le responda, como no le ha respondido, va a continuar con otra actividad.
B8: TSER | C8: CONTABILIDAD | D8: ANALISTA CONTABLE 2 EXPORTADORAS | E8: GERALDINE NAULA | F8: 45971 | I8: LIQUIDACIÓN - GASTOS ARROZ | J8: =IFERROR(VLOOKUP(MUESTREO_LABORAL_A2[[#This Row],[ACTIVIDAD]],'Lista Maestra'!$D$6:$F$190,3,0),"") -> LIQUIDACIÓN DE GASTOS | K8: =IFERROR(VLOOKUP(MUESTREO_LABORAL_A2[[#This Row],[ACTIVIDAD]],'Lista Maestra'!$D$6:$F$190,2,0),"") -> 0 | L8: ENC | N8: 0.41041667 | O8: 0.52083333 | P8: =IF(MUESTREO_LABORAL_A2[[#This Row],[TIEMPO INICIO]]="","",(MUESTREO_LABORAL_A2[[#This Row],[TIEMPO FIN]]-MUESTREO_LABORAL_A2[[#This Row],[TIEMPO INICIO]])*24) -> 2.65 | Q8: 11:14 vino Jennifer a decirle algo relacionado al arroz a Geraldine. Lo que sucede es que Jennifer tiene que desaplicar unas facuras (cuyo total es de 268.50 USD) que no corresponde a la cosecha puesto que a la cosecha del PAN corresponde algo relacionado al de la ISLA. | R8: Se puede crear una solución integral para establecer una mejor comunicación entre José Terán (de servicios auxiliares) y Contabilidad puesto que actualmente la gestión se la realiza mediante un papel y está presto a errores y confusiones.
B9: TSER | C9: CONTABILIDAD | D9: ANALISTA CONTABLE 2 EXPORTADORAS | E9: GERALDINE NAULA | F9: 45971 | I9: ALIMENTACIÓN | J9: =IFERROR(VLOOKUP(MUESTREO_LABORAL_A2[[#This Row],[ACTIVIDAD]],'Lista Maestra'!$D$6:$F$190,3,0),"") -> ALIMENTACIÓN | K9: =IFERROR(VLOOKUP(MUESTREO_LABORAL_A2[[#This Row],[ACTIVIDAD]],'Lista Maestra'!$D$6:$F$190,2,0),"") -> ALIMENTARSE | L9: ALIMENTACIÓN | N9: 0.52083333 | O9: 0.5625 | P9: =IF(MUESTREO_LABORAL_A2[[#This Row],[TIEMPO INICIO]]="","",(MUESTREO_LABORAL_A2[[#This Row],[TIEMPO FIN]]-MUESTREO_LABORAL_A2[[#This Row],[TIEMPO INICIO]])*24) -> 1
B10: TSER | C10: CONTABILIDAD | D10: ANALISTA CONTABLE 2 EXPORTADORAS | E10: GERALDINE NAULA | F10: 45971 | I10: NECESIDADES BIOLÓGICAS | J10: =IFERROR(VLOOKUP(MUESTREO_LABORAL_A2[[#This Row],[ACTIVIDAD]],'Lista Maestra'!$D$6:$F$190,3,0),"") -> NECESIDADES BIOLÓGICAS | K10: =IFERROR(VLOOKUP(MUESTREO_LABORAL_A2[[#This Row],[ACTIVIDAD]],'Lista Maestra'!$D$6:$F$190,2,0),"") -> PROCESO DE MICCIÓN Y AGREGADOS | L10: SA | N10: 0.5625 | O10: 0.56458333 | P10: =IF(MUESTREO_LABORAL_A2[[#This Row],[TIEMPO INICIO]]="","",(MUESTREO_LABORAL_A2[[#This Row],[TIEMPO FIN]]-MUESTREO_LABORAL_A2[[#This Row],[TIEMPO INICIO]])*24) -> 0.05
B11: TSER | C11: CONTABILIDAD | D11: ANALISTA CONTABLE 2 EXPORTADORAS | E11: GERALDINE NAULA | F11: 45971 | I11: LIQUIDACIÓN - GASTOS ARROZ | J11: =IFERROR(VLOOKUP(MUESTREO_LABORAL_A2[[#This Row],[ACTIVIDAD]],'Lista Maestra'!$D$6:$F$190,3,0),"") -> LIQUIDACIÓN DE GASTOS | K11: =IFERROR(VLOOKUP(MUESTREO_LABORAL_A2[[#This Row],[ACTIVIDAD]],'Lista Maestra'!$D$6:$F$190,2,0),"") -> 0 | L11: CON ACTIVIDAD | N11: 0.56458333 | O11: 0.57291667 | P11: =IF(MUESTREO_LABORAL_A2[[#This Row],[TIEMPO INICIO]]="","",(MUESTREO_LABORAL_A2[[#This Row],[TIEMPO FIN]]-MUESTREO_LABORAL_A2[[#This Row],[TIEMPO INICIO]])*24) -> 0.2 | Q11: José Terán solicita anticipos a financiero a medida de la cosecha del arroz, y hay facturas que nos llegan al sri y éstas nos llegan al SRI.
B12: TSER | C12: CONTABILIDAD | D12: ANALISTA CONTABLE 2 EXPORTADORAS | E12: GERALDINE NAULA | F12: 45971 | I12: DEFINICIÓN | J12: =IFERROR(VLOOKUP(MUESTREO_LABORAL_A2[[#This Row],[ACTIVIDAD]],'Lista Maestra'!$D$6:$F$190,3,0),"") -> DEFINICIÓN | K12: =IFERROR(VLOOKUP(MUESTREO_LABORAL_A2[[#This Row],[ACTIVIDAD]],'Lista Maestra'!$D$6:$F$190,2,0),"") -> DEFINIR PROCESOS Y CRITERIOS INGENIERILES | L12: DEFINICIÓN | N12: 0.57291667 | O12: 0.58055556 | P12: =IF(MUESTREO_LABORAL_A2[[#This Row],[TIEMPO INICIO]]="","",(MUESTREO_LABORAL_A2[[#This Row],[TIEMPO FIN]]-MUESTREO_LABORAL_A2[[#This Row],[TIEMPO INICIO]])*24) -> 0.18333333 | Q12: Geraldine me explica el tema de la cosecha del arroz.
B13: TSER | C13: CONTABILIDAD | D13: ANALISTA CONTABLE 2 EXPORTADORAS | E13: GERALDINE NAULA | F13: 45971 | G13: CONTABILIDAD | H13: ASISTENTE CONTABLE | I13: SOPORTE INGRESO DE FACTURAS DE COMPRAS | J13: =IFERROR(VLOOKUP(MUESTREO_LABORAL_A2[[#This Row],[ACTIVIDAD]],'Lista Maestra'!$D$6:$F$190,3,0),"") -> SUPERVISIÓN EN CIERRE | K13: =IFERROR(VLOOKUP(MUESTREO_LABORAL_A2[[#This Row],[ACTIVIDAD]],'Lista Maestra'!$D$6:$F$190,2,0),"") -> 0 | L13: CON ACTIVIDAD | N13: 0.58055556 | O13: 0.62222222 | P13: =IF(MUESTREO_LABORAL_A2[[#This Row],[TIEMPO INICIO]]="","",(MUESTREO_LABORAL_A2[[#This Row],[TIEMPO FIN]]-MUESTREO_LABORAL_A2[[#This Row],[TIEMPO INICIO]])*24) -> 1 | Q13: Le da soporte a Marly porque está en su periodo de lactancia.
B14: TSER | C14: CONTABILIDAD | D14: ANALISTA CONTABLE 2 EXPORTADORAS | E14: GERALDINE NAULA | F14: 45971 | I14: NECESIDADES BIOLÓGICAS | J14: =IFERROR(VLOOKUP(MUESTREO_LABORAL_A2[[#This Row],[ACTIVIDAD]],'Lista Maestra'!$D$6:$F$190,3,0),"") -> NECESIDADES BIOLÓGICAS | K14: =IFERROR(VLOOKUP(MUESTREO_LABORAL_A2[[#This Row],[ACTIVIDAD]],'Lista Maestra'!$D$6:$F$190,2,0),"") -> PROCESO DE MICCIÓN Y AGREGADOS | L14: SA | N14: 0.62222222 | O14: 0.625 | P14: =IF(MUESTREO_LABORAL_A2[[#This Row],[TIEMPO INICIO]]="","",(MUESTREO_LABORAL_A2[[#This Row],[TIEMPO FIN]]-MUESTREO_LABORAL_A2[[#This Row],[TIEMPO INICIO]])*24) -> 0.066666667
B15: TSER | C15: CONTABILIDAD | D15: ANALISTA CONTABLE 2 EXPORTADORAS | E15: GERALDINE NAULA | F15: 45972 | I15: FACTURACIÓN CIF BANANO A CLIENTES EN MULTINATIONAL | J15: =IFERROR(VLOOKUP(MUESTREO_LABORAL_A2[[#This Row],[ACTIVIDAD]],'Lista Maestra'!$D$6:$F$190,3,0),"") -> FACTURACIÓN A CLIENTES | K15: =IFERROR(VLOOKUP(MUESTREO_LABORAL_A2[[#This Row],[ACTIVIDAD]],'Lista Maestra'!$D$6:$F$190,2,0),"") -> ELABORACIÓN SEMANAL DE FACTURAS DE BANANO PARA CLIENTES INTERNACIONALES EN MULTINATIONAL, TRABAJANDO CON LOS REPORTES DE TRÁMITES DE LA SEMANA, DETALLE DE CONSOLIDACIÓN EN FTL Y B/LS CON CIERRE SEMANAL CORRESPONDIENTE. | L15: CON ACTIVIDAD | N15: 0.35416667 | O15: 0.39444444 | P15: =IF(MUESTREO_LABORAL_A2[[#This Row],[TIEMPO INICIO]]="","",(MUESTREO_LABORAL_A2[[#This Row],[TIEMPO FIN]]-MUESTREO_LABORAL_A2[[#This Row],[TIEMPO INICIO]])*24) -> 0.96666667
B16: TSER | C16: CONTABILIDAD | D16: ANALISTA CONTABLE 2 EXPORTADORAS | E16: GERALDINE NAULA | F16: 45972 | I16: CONTROL DE CUENTAS POR PAGAR Y REVISIÓN DE GASTOS OPERATIVOS EN EXPORTADORAS | J16: =IFERROR(VLOOKUP(MUESTREO_LABORAL_A2[[#This Row],[ACTIVIDAD]],'Lista Maestra'!$D$6:$F$190,3,0),"") -> SUPERVISIÓN EN CIERRE | K16: =IFERROR(VLOOKUP(MUESTREO_LABORAL_A2[[#This Row],[ACTIVIDAD]],'Lista Maestra'!$D$6:$F$190,2,0),"") -> SE REVISA Y CONTROLA LA INFORMACIÓN DE LAS CUENTAS POR PAGAR DE LAS EXPORTADORAS, VERIFICANDO QUE LAS FACTURAS DE COMPRA Y GASTOS OPERATIVOS ESTÉN CORRECTAMENTE REGISTRADOS, APROBADOS Y RESPALDADOS. SE REALIZAN SEGUIMIENTOS A LOS PROVEEDORES Y SE CONFIRMA QUE LOS VALORES COINCIDAN CON LOS REGISTROS CONTABLES. | L16: CON ACTIVIDAD | N16: 0.39444444 | O16: 0.40138889 | P16: =IF(MUESTREO_LABORAL_A2[[#This Row],[TIEMPO INICIO]]="","",(MUESTREO_LABORAL_A2[[#This Row],[TIEMPO FIN]]-MUESTREO_LABORAL_A2[[#This Row],[TIEMPO INICIO]])*24) -> 0.16666667 | Q16: ahorita pare un rato lo de la facturacion porque ingresare un NC que me solicito angelo eso es cuentas por pagar
B17: TSER | C17: CONTABILIDAD | D17: ANALISTA CONTABLE 2 EXPORTADORAS | E17: GERALDINE NAULA | F17: 45972 | I17: FACTURACIÓN CIF BANANO A CLIENTES EN MULTINATIONAL | J17: =IFERROR(VLOOKUP(MUESTREO_LABORAL_A2[[#This Row],[ACTIVIDAD]],'Lista Maestra'!$D$6:$F$190,3,0),"") -> FACTURACIÓN A CLIENTES | K17: =IFERROR(VLOOKUP(MUESTREO_LABORAL_A2[[#This Row],[ACTIVIDAD]],'Lista Maestra'!$D$6:$F$190,2,0),"") -> ELABORACIÓN SEMANAL DE FACTURAS DE BANANO PARA CLIENTES INTERNACIONALES EN MULTINATIONAL, TRABAJANDO CON LOS REPORTES DE TRÁMITES DE LA SEMANA, DETALLE DE CONSOLIDACIÓN EN FTL Y B/LS CON CIERRE SEMANAL CORRESPONDIENTE. | L17: CON ACTIVIDAD | N17: 0.40138889 | O17: 0.51111111 | P17: =IF(MUESTREO_LABORAL_A2[[#This Row],[TIEMPO INICIO]]="","",(MUESTREO_LABORAL_A2[[#This Row],[TIEMPO FIN]]-MUESTREO_LABORAL_A2[[#This Row],[TIEMPO INICIO]])*24) -> 2.6333333
B18: TSER | C18: CONTABILIDAD | D18: ANALISTA CONTABLE 2 EXPORTADORAS | E18: GERALDINE NAULA | F18: 45972 | G18: CERTIFICACIONES | H18: ASISTENTE EN CERTIFICACIONES | I18: CAPACITACIÓN Y ASISTENCIA EN SAP A OTROS DEPARTAMENTOS | J18: =IFERROR(VLOOKUP(MUESTREO_LABORAL_A2[[#This Row],[ACTIVIDAD]],'Lista Maestra'!$D$6:$F$190,3,0),"") -> SOPORTE CONTABLE | K18: =IFERROR(VLOOKUP(MUESTREO_LABORAL_A2[[#This Row],[ACTIVIDAD]],'Lista Maestra'!$D$6:$F$190,2,0),"") -> SE BRINDA CAPACITACIÓN Y ASISTENCIA EN EL USO DE SAP A OTROS DEPARTAMENTOS, EXPLICANDO PROCESOS CONTABLES, FUNCIONALIDADES DEL SISTEMA Y PROCEDIMIENTOS PARA EL REGISTRO. | L18: CON ACTIVIDAD | N18: 0.51111111 | O18: 0.51805556 | P18: =IF(MUESTREO_LABORAL_A2[[#This Row],[TIEMPO INICIO]]="","",(MUESTREO_LABORAL_A2[[#This Row],[TIEMPO FIN]]-MUESTREO_LABORAL_A2[[#This Row],[TIEMPO INICIO]])*24) -> 0.16666667 | Q18: Holis Jonathan ahorita estoy dando soporte a otro dep es certificaciones en este caso me estan solicitando un ruc
B19: TSER | C19: CONTABILIDAD | D19: ANALISTA CONTABLE 2 EXPORTADORAS | E19: GERALDINE NAULA | F19: 45972 | I19: SOPORTE INGRESO DE FACTURAS DE COMPRAS | J19: =IFERROR(VLOOKUP(MUESTREO_LABORAL_A2[[#This Row],[ACTIVIDAD]],'Lista Maestra'!$D$6:$F$190,3,0),"") -> SUPERVISIÓN EN CIERRE | K19: =IFERROR(VLOOKUP(MUESTREO_LABORAL_A2[[#This Row],[ACTIVIDAD]],'Lista Maestra'!$D$6:$F$190,2,0),"") -> 0 | L19: CON ACTIVIDAD | N19: 0.51805556 | O19: 0.52083333 | P19: =IF(MUESTREO_LABORAL_A2[[#This Row],[TIEMPO INICIO]]="","",(MUESTREO_LABORAL_A2[[#This Row],[TIEMPO FIN]]-MUESTREO_LABORAL_A2[[#This Row],[TIEMPO INICIO]])*24) -> 0.066666667 | Q19: ya le di la info a Ruben ahorita me escribio angelo para que ingrese una fc de consorcio entonces eso hare es CxP igual pero aun falta AFC porque jenn aun no me confirma un dato apenas jenn me confirme sigo con eso
B20: TSER | C20: CONTABILIDAD | D20: ANALISTA CONTABLE 2 EXPORTADORAS | E20: GERALDINE NAULA | F20: 45972 | I20: DEFINICIÓN | J20: =IFERROR(VLOOKUP(MUESTREO_LABORAL_A2[[#This Row],[ACTIVIDAD]],'Lista Maestra'!$D$6:$F$190,3,0),"") -> DEFINICIÓN | K20: =IFERROR(VLOOKUP(MUESTREO_LABORAL_A2[[#This Row],[ACTIVIDAD]],'Lista Maestra'!$D$6:$F$190,2,0),"") -> DEFINIR PROCESOS Y CRITERIOS INGENIERILES | L20: DEFINICIÓN | N20: 0.5625 | O20: 0.58194444 | P20: =IF(MUESTREO_LABORAL_A2[[#This Row],[TIEMPO INICIO]]="","",(MUESTREO_LABORAL_A2[[#This Row],[TIEMPO FIN]]-MUESTREO_LABORAL_A2[[#This Row],[TIEMPO INICIO]])*24) -> 0.46666667 | Q20: Definimos ciertas actividades pendientes y aquellas en las que da soporte a otros departamentos o compañeros de trabajo.
B21: TSER | C21: CONTABILIDAD | D21: ANALISTA CONTABLE 2 EXPORTADORAS | E21: GERALDINE NAULA | F21: 45972 | I21: ASIENTOS POR DESCUENTOS A EMPLEADOS MEDIANTE ROL | J21: =IFERROR(VLOOKUP(MUESTREO_LABORAL_A2[[#This Row],[ACTIVIDAD]],'Lista Maestra'!$D$6:$F$190,3,0),"") -> DESCUENTOS DE NÓMINA | K21: =IFERROR(VLOOKUP(MUESTREO_LABORAL_A2[[#This Row],[ACTIVIDAD]],'Lista Maestra'!$D$6:$F$190,2,0),"") -> REGISTRO Y ANÁLISIS DE ASIENTOS DE DIARIO O DE RECLASIFICACIÓN EN CUENTAS POR COBRAR DE EMPLEADOS POR DESCUENTOS INDICADOS POR EL ÁREA DE RRHH, VERIFICANDO LA CONSISTENCIA DE MONTOS, CLASIFICACIÓN CONTABLE CORRECTA | L21: CON ACTIVIDAD | N21: 0.58194444 | O21: 0.625 | P21: =IF(MUESTREO_LABORAL_A2[[#This Row],[TIEMPO INICIO]]="","",(MUESTREO_LABORAL_A2[[#This Row],[TIEMPO FIN]]-MUESTREO_LABORAL_A2[[#This Row],[TIEMPO INICIO]])*24) -> 1.0333333 | Q21: ahorita voy a registrar unos descuentos de nómina
B22: TSER | C22: CONTABILIDAD | D22: ANALISTA CONTABLE 2 EXPORTADORAS | E22: GERALDINE NAULA | F22: 45973 | I22: FACTURACIÓN CIF BANANO A CLIENTES EN MULTINATIONAL | J22: =IFERROR(VLOOKUP(MUESTREO_LABORAL_A2[[#This Row],[ACTIVIDAD]],'Lista Maestra'!$D$6:$F$190,3,0),"") -> FACTURACIÓN A CLIENTES | K22: =IFERROR(VLOOKUP(MUESTREO_LABORAL_A2[[#This Row],[ACTIVIDAD]],'Lista Maestra'!$D$6:$F$190,2,0),"") -> ELABORACIÓN SEMANAL DE FACTURAS DE BANANO PARA CLIENTES INTERNACIONALES EN MULTINATIONAL, TRABAJANDO CON LOS REPORTES DE TRÁMITES DE LA SEMANA, DETALLE DE CONSOLIDACIÓN EN FTL Y B/LS CON CIERRE SEMANAL CORRESPONDIENTE. | L22: CON ACTIVIDAD | N22: 0.35416667 | O22: 0.39722222 | P22: =IF(MUESTREO_LABORAL_A2[[#This Row],[TIEMPO INICIO]]="","",(MUESTREO_LABORAL_A2[[#This Row],[TIEMPO FIN]]-MUESTREO_LABORAL_A2[[#This Row],[TIEMPO INICIO]])*24) -> 1.0333333
B23: TSER | C23: CONTABILIDAD | D23: ANALISTA CONTABLE 2 EXPORTADORAS | E23: GERALDINE NAULA | F23: 45973 | I23: NECESIDADES BIOLÓGICAS | J23: =IFERROR(VLOOKUP(MUESTREO_LABORAL_A2[[#This Row],[ACTIVIDAD]],'Lista Maestra'!$D$6:$F$190,3,0),"") -> NECESIDADES BIOLÓGICAS | K23: =IFERROR(VLOOKUP(MUESTREO_LABORAL_A2[[#This Row],[ACTIVIDAD]],'Lista Maestra'!$D$6:$F$190,2,0),"") -> PROCESO DE MICCIÓN Y AGREGADOS | N23: 0.39722222 | O23: 0.40069444 | P23: =IF(MUESTREO_LABORAL_A2[[#This Row],[TIEMPO INICIO]]="","",(MUESTREO_LABORAL_A2[[#This Row],[TIEMPO FIN]]-MUESTREO_LABORAL_A2[[#This Row],[TIEMPO INICIO]])*24) -> 0.083333333
B24: TSER | C24: CONTABILIDAD | D24: ANALISTA CONTABLE 2 EXPORTADORAS | E24: GERALDINE NAULA | F24: 45973 | I24: FACTURACIÓN CIF BANANO A CLIENTES EN MULTINATIONAL | J24: =IFERROR(VLOOKUP(MUESTREO_LABORAL_A2[[#This Row],[ACTIVIDAD]],'Lista Maestra'!$D$6:$F$190,3,0),"") -> FACTURACIÓN A CLIENTES | K24: =IFERROR(VLOOKUP(MUESTREO_LABORAL_A2[[#This Row],[ACTIVIDAD]],'Lista Maestra'!$D$6:$F$190,2,0),"") -> ELABORACIÓN SEMANAL DE FACTURAS DE BANANO PARA CLIENTES INTERNACIONALES EN MULTINATIONAL, TRABAJANDO CON LOS REPORTES DE TRÁMITES DE LA SEMANA, DETALLE DE CONSOLIDACIÓN EN FTL Y B/LS CON CIERRE SEMANAL CORRESPONDIENTE. | L24: CON ACTIVIDAD | N24: 0.40069444 | O24: 0.44027778 | P24: =IF(MUESTREO_LABORAL_A2[[#This Row],[TIEMPO INICIO]]="","",(MUESTREO_LABORAL_A2[[#This Row],[TIEMPO FIN]]-MUESTREO_LABORAL_A2[[#This Row],[TIEMPO INICIO]])*24) -> 0.95
B25: TSER | C25: CONTABILIDAD | D25: ANALISTA CONTABLE 2 EXPORTADORAS | E25: GERALDINE NAULA | F25: 45973 | I25: RECLASIFICACIONES CONTABLES Y AJUSTES MENSUALES | J25: =IFERROR(VLOOKUP(MUESTREO_LABORAL_A2[[#This Row],[ACTIVIDAD]],'Lista Maestra'!$D$6:$F$190,3,0),"") -> ANÁLISIS DE CUENTAS | K25: =IFERROR(VLOOKUP(MUESTREO_LABORAL_A2[[#This Row],[ACTIVIDAD]],'Lista Maestra'!$D$6:$F$190,2,0),"") -> SE REALIZAN RECLASIFICACIONES CONTABLES Y AJUSTES MENSUALES SEGÚN LAS OBSERVACIONES DEL ÁREA CONTABLE O AUDITORÍA, CORRIGIENDO REGISTROS MAL CLASIFICADOS O INCONSISTENCIAS DETECTADAS. | L25: CON ACTIVIDAD | N25: 0.44027778 | O25: 0.44375 | P25: =IF(MUESTREO_LABORAL_A2[[#This Row],[TIEMPO INICIO]]="","",(MUESTREO_LABORAL_A2[[#This Row],[TIEMPO FIN]]-MUESTREO_LABORAL_A2[[#This Row],[TIEMPO INICIO]])*24) -> 0.083333333
B26: TSER | C26: CONTABILIDAD | D26: ANALISTA CONTABLE 2 EXPORTADORAS | E26: GERALDINE NAULA | F26: 45973 | I26: FACTURACIÓN CIF BANANO A CLIENTES EN MULTINATIONAL | J26: =IFERROR(VLOOKUP(MUESTREO_LABORAL_A2[[#This Row],[ACTIVIDAD]],'Lista Maestra'!$D$6:$F$190,3,0),"") -> FACTURACIÓN A CLIENTES | K26: =IFERROR(VLOOKUP(MUESTREO_LABORAL_A2[[#This Row],[ACTIVIDAD]],'Lista Maestra'!$D$6:$F$190,2,0),"") -> ELABORACIÓN SEMANAL DE FACTURAS DE BANANO PARA CLIENTES INTERNACIONALES EN MULTINATIONAL, TRABAJANDO CON LOS REPORTES DE TRÁMITES DE LA SEMANA, DETALLE DE CONSOLIDACIÓN EN FTL Y B/LS CON CIERRE SEMANAL CORRESPONDIENTE. | L26: CON ACTIVIDAD | N26: 0.44375 | O26: 0.47361111 | P26: =IF(MUESTREO_LABORAL_A2[[#This Row],[TIEMPO INICIO]]="","",(MUESTREO_LABORAL_A2[[#This Row],[TIEMPO FIN]]-MUESTREO_LABORAL_A2[[#This Row],[TIEMPO INICIO]])*24) -> 0.71666667 | Q26: A la espera de la información de Jennifer Medranda. SIIM MAERSK
B27: TSER | C27: CONTABILIDAD | D27: ANALISTA CONTABLE 2 EXPORTADORAS | E27: GERALDINE NAULA | F27: 45973 | I27: FACTURACIÓN CIF PLÁTANO A CLIENTES EN MULTINATIONAL | J27: =IFERROR(VLOOKUP(MUESTREO_LABORAL_A2[[#This Row],[ACTIVIDAD]],'Lista Maestra'!$D$6:$F$190,3,0),"") -> FACTURACIÓN A CLIENTES | K27: =IFERROR(VLOOKUP(MUESTREO_LABORAL_A2[[#This Row],[ACTIVIDAD]],'Lista Maestra'!$D$6:$F$190,2,0),"") -> ELABORACIÓN SEMANAL DE FACTURAS DE PLATANO PARA CLIENTES INTERNACIONALES EN MULTINATIONAL, TRABAJANDO CON LOS REPORTES DE TRÁMITES DE LA SEMANA, DETALLE DE CONSOLIDACIÓN EN FTL Y B/LS CON CIERRE SEMANAL CORRESPONDIENTE. | L27: CON ACTIVIDAD | N27: 0.47361111 | O27: 0.4875 | P27: =IF(MUESTREO_LABORAL_A2[[#This Row],[TIEMPO INICIO]]="","",(MUESTREO_LABORAL_A2[[#This Row],[TIEMPO FIN]]-MUESTREO_LABORAL_A2[[#This Row],[TIEMPO INICIO]])*24) -> 0.33333333 | Q27: A la espera de la información de Jennifer Medranda. P&A
B28: TSER | C28: CONTABILIDAD | D28: ANALISTA CONTABLE 2 EXPORTADORAS | E28: GERALDINE NAULA | F28: 45973 | I28: COMPARATIVO VENTAS MLC Y DECLARACION COFACE | J28: =IFERROR(VLOOKUP(MUESTREO_LABORAL_A2[[#This Row],[ACTIVIDAD]],'Lista Maestra'!$D$6:$F$190,3,0),"") -> ANÁLISIS DE VENTAS | K28: =IFERROR(VLOOKUP(MUESTREO_LABORAL_A2[[#This Row],[ACTIVIDAD]],'Lista Maestra'!$D$6:$F$190,2,0),"") -> REALIZAR REPORTE, ANALISIS, COMPARACIÓN Y REVISIÓN DE LA INFORMACIÓN RECIBIDA POR CORREO DEL ÁREA FINANCIERA, VERIFICANDO QUE LO DECLARADO A COFACE COINCIDA CON LAS VENTAS REGISTRADAS EN LA CONTABILIDAD POR CLIENTE EN MULTINATIONAL. | L28: CON ACTIVIDAD | N28: 0.4875 | O28: 0.51388889 | P28: =IF(MUESTREO_LABORAL_A2[[#This Row],[TIEMPO INICIO]]="","",(MUESTREO_LABORAL_A2[[#This Row],[TIEMPO FIN]]-MUESTREO_LABORAL_A2[[#This Row],[TIEMPO INICIO]])*24) -> 0.63333333
B29: TSER | C29: CONTABILIDAD | D29: ANALISTA CONTABLE 2 EXPORTADORAS | E29: GERALDINE NAULA | F29: 45973 | I29: NECESIDADES BIOLÓGICAS | J29: =IFERROR(VLOOKUP(MUESTREO_LABORAL_A2[[#This Row],[ACTIVIDAD]],'Lista Maestra'!$D$6:$F$190,3,0),"") -> NECESIDADES BIOLÓGICAS | K29: =IFERROR(VLOOKUP(MUESTREO_LABORAL_A2[[#This Row],[ACTIVIDAD]],'Lista Maestra'!$D$6:$F$190,2,0),"") -> PROCESO DE MICCIÓN Y AGREGADOS | L29: CON ACTIVIDAD | N29: 0.51388889 | O29: 0.51875 | P29: =IF(MUESTREO_LABORAL_A2[[#This Row],[TIEMPO INICIO]]="","",(MUESTREO_LABORAL_A2[[#This Row],[TIEMPO FIN]]-MUESTREO_LABORAL_A2[[#This Row],[TIEMPO INICIO]])*24) -> 0.11666667
B30: TSER | C30: CONTABILIDAD | D30: ANALISTA CONTABLE 2 EXPORTADORAS | E30: GERALDINE NAULA | F30: 45973 | I30: EMISIÓN CERTIFICADOS DE EXPORTACIÓN | J30: =IFERROR(VLOOKUP(MUESTREO_LABORAL_A2[[#This Row],[ACTIVIDAD]],'Lista Maestra'!$D$6:$F$190,3,0),"") -> EMISIÓN CERTIFICADOS | K30: =IFERROR(VLOOKUP(MUESTREO_LABORAL_A2[[#This Row],[ACTIVIDAD]],'Lista Maestra'!$D$6:$F$190,2,0),"") -> ELABORACIÓN DE CERTIFICADOS PARA PRODUCTORES SEGÚN LOS MESES SOLICITADOS, INCLUYENDO EL DETALLE DE DAE, NÚMERO DE FACTURA DE VENTA, CANTIDAD DE CAJAS EXPORTADAS, FECHA DE CIERRE DE LAS DAE, VALOR TOTAL EN USD Y FACTURA DE COMPRA DEL PROVEEDOR. | L30: CON ACTIVIDAD | N30: 0.51875 | O30: 0.52083333 | P30: =IF(MUESTREO_LABORAL_A2[[#This Row],[TIEMPO INICIO]]="","",(MUESTREO_LABORAL_A2[[#This Row],[TIEMPO FIN]]-MUESTREO_LABORAL_A2[[#This Row],[TIEMPO INICIO]])*24) -> 0.05
B31: TSER | C31: CONTABILIDAD | D31: ANALISTA CONTABLE 2 EXPORTADORAS | E31: GERALDINE NAULA | F31: 45973 | I31: ALIMENTACIÓN | J31: =IFERROR(VLOOKUP(MUESTREO_LABORAL_A2[[#This Row],[ACTIVIDAD]],'Lista Maestra'!$D$6:$F$190,3,0),"") -> ALIMENTACIÓN | K31: =IFERROR(VLOOKUP(MUESTREO_LABORAL_A2[[#This Row],[ACTIVIDAD]],'Lista Maestra'!$D$6:$F$190,2,0),"") -> ALIMENTARSE | L31: ALIMENTACIÓN | N31: 0.52083333 | O31: 0.5625 | P31: =IF(MUESTREO_LABORAL_A2[[#This Row],[TIEMPO INICIO]]="","",(MUESTREO_LABORAL_A2[[#This Row],[TIEMPO FIN]]-MUESTREO_LABORAL_A2[[#This Row],[TIEMPO INICIO]])*24) -> 1
B32: TSER | C32: CONTABILIDAD | D32: ANALISTA CONTABLE 2 EXPORTADORAS | E32: GERALDINE NAULA | F32: 45973 | I32: FACTURACIÓN CIF BANANO A CLIENTES EN MULTINATIONAL | J32: =IFERROR(VLOOKUP(MUESTREO_LABORAL_A2[[#This Row],[ACTIVIDAD]],'Lista Maestra'!$D$6:$F$190,3,0),"") -> FACTURACIÓN A CLIENTES | K32: =IFERROR(VLOOKUP(MUESTREO_LABORAL_A2[[#This Row],[ACTIVIDAD]],'Lista Maestra'!$D$6:$F$190,2,0),"") -> ELABORACIÓN SEMANAL DE FACTURAS DE BANANO PARA CLIENTES INTERNACIONALES EN MULTINATIONAL, TRABAJANDO CON LOS REPORTES DE TRÁMITES DE LA SEMANA, DETALLE DE CONSOLIDACIÓN EN FTL Y B/LS CON CIERRE SEMANAL CORRESPONDIENTE. | L32: CON ACTIVIDAD | N32: 0.5625 | O32: 0.58263889 | P32: =IF(MUESTREO_LABORAL_A2[[#This Row],[TIEMPO INICIO]]="","",(MUESTREO_LABORAL_A2[[#This Row],[TIEMPO FIN]]-MUESTREO_LABORAL_A2[[#This Row],[TIEMPO INICIO]])*24) -> 0.48333333
B33: TSER | C33: CONTABILIDAD | D33: ANALISTA CONTABLE 2 EXPORTADORAS | E33: GERALDINE NAULA | F33: 45973 | I33: EMISIÓN CERTIFICADOS DE EXPORTACIÓN | J33: =IFERROR(VLOOKUP(MUESTREO_LABORAL_A2[[#This Row],[ACTIVIDAD]],'Lista Maestra'!$D$6:$F$190,3,0),"") -> EMISIÓN CERTIFICADOS | K33: =IFERROR(VLOOKUP(MUESTREO_LABORAL_A2[[#This Row],[ACTIVIDAD]],'Lista Maestra'!$D$6:$F$190,2,0),"") -> ELABORACIÓN DE CERTIFICADOS PARA PRODUCTORES SEGÚN LOS MESES SOLICITADOS, INCLUYENDO EL DETALLE DE DAE, NÚMERO DE FACTURA DE VENTA, CANTIDAD DE CAJAS EXPORTADAS, FECHA DE CIERRE DE LAS DAE, VALOR TOTAL EN USD Y FACTURA DE COMPRA DEL PROVEEDOR. | L33: CON ACTIVIDAD | N33: 0.58263889 | O33: 0.625 | P33: =IF(MUESTREO_LABORAL_A2[[#This Row],[TIEMPO INICIO]]="","",(MUESTREO_LABORAL_A2[[#This Row],[TIEMPO FIN]]-MUESTREO_LABORAL_A2[[#This Row],[TIEMPO INICIO]])*24) -> 1.0166667
B34: TSER | C34: CONTABILIDAD | D34: ANALISTA CONTABLE 2 EXPORTADORAS | E34: GERALDINE NAULA | F34: 45974 | I34: FACTURACIÓN CIF BANANO A CLIENTES EN MULTINATIONAL | J34: =IFERROR(VLOOKUP(MUESTREO_LABORAL_A2[[#This Row],[ACTIVIDAD]],'Lista Maestra'!$D$6:$F$190,3,0),"") -> FACTURACIÓN A CLIENTES | K34: =IFERROR(VLOOKUP(MUESTREO_LABORAL_A2[[#This Row],[ACTIVIDAD]],'Lista Maestra'!$D$6:$F$190,2,0),"") -> ELABORACIÓN SEMANAL DE FACTURAS DE BANANO PARA CLIENTES INTERNACIONALES EN MULTINATIONAL, TRABAJANDO CON LOS REPORTES DE TRÁMITES DE LA SEMANA, DETALLE DE CONSOLIDACIÓN EN FTL Y B/LS CON CIERRE SEMANAL CORRESPONDIENTE. | L34: CON ACTIVIDAD | N34: 0.35416667 | O34: 0.37708333 | P34: =IF(MUESTREO_LABORAL_A2[[#This Row],[TIEMPO INICIO]]="","",(MUESTREO_LABORAL_A2[[#This Row],[TIEMPO FIN]]-MUESTREO_LABORAL_A2[[#This Row],[TIEMPO INICIO]])*24) -> 0.55
B35: TSER | C35: CONTABILIDAD | D35: ANALISTA CONTABLE 2 EXPORTADORAS | E35: GERALDINE NAULA | F35: 45974 | I35: FACTURACIÓN CIF PLÁTANO A CLIENTES EN MULTINATIONAL | J35: =IFERROR(VLOOKUP(MUESTREO_LABORAL_A2[[#This Row],[ACTIVIDAD]],'Lista Maestra'!$D$6:$F$190,3,0),"") -> FACTURACIÓN A CLIENTES | K35: =IFERROR(VLOOKUP(MUESTREO_LABORAL_A2[[#This Row],[ACTIVIDAD]],'Lista Maestra'!$D$6:$F$190,2,0),"") -> ELABORACIÓN SEMANAL DE FACTURAS DE PLATANO PARA CLIENTES INTERNACIONALES EN MULTINATIONAL, TRABAJANDO CON LOS REPORTES DE TRÁMITES DE LA SEMANA, DETALLE DE CONSOLIDACIÓN EN FTL Y B/LS CON CIERRE SEMANAL CORRESPONDIENTE. | L35: CON ACTIVIDAD | N35: 0.37708333 | O35: 0.40208333 | P35: =IF(MUESTREO_LABORAL_A2[[#This Row],[TIEMPO INICIO]]="","",(MUESTREO_LABORAL_A2[[#This Row],[TIEMPO FIN]]-MUESTREO_LABORAL_A2[[#This Row],[TIEMPO INICIO]])*24) -> 0.6
B36: TSER | C36: CONTABILIDAD | D36: ANALISTA CONTABLE 2 EXPORTADORAS | E36: GERALDINE NAULA | F36: 45974 | I36: SOPORTE MEDIANTE AUDITORÍA EXTERNAS E INTERNAS | J36: =IFERROR(VLOOKUP(MUESTREO_LABORAL_A2[[#This Row],[ACTIVIDAD]],'Lista Maestra'!$D$6:$F$190,3,0),"") -> SOPORTE AUDITORÍA | K36: =IFERROR(VLOOKUP(MUESTREO_LABORAL_A2[[#This Row],[ACTIVIDAD]],'Lista Maestra'!$D$6:$F$190,2,0),"") -> PROPORCIONAR SOPORTE EN AUDITORÍAS TRIBUTARIAS, DE CARBONO NEUTRO Y OTROS PROCESOS DE CONTROL FINANCIERO. | L36: CON ACTIVIDAD | N36: 0.40208333 | O36: 0.44861111 | P36: =IF(MUESTREO_LABORAL_A2[[#This Row],[TIEMPO INICIO]]="","",(MUESTREO_LABORAL_A2[[#This Row],[TIEMPO FIN]]-MUESTREO_LABORAL_A2[[#This Row],[TIEMPO INICIO]])*24) -> 1.1166667
B37: TSER | C37: CONTABILIDAD | D37: ANALISTA CONTABLE 2 EXPORTADORAS | E37: GERALDINE NAULA | F37: 45974 | I37: ELABORACIÓN DE REPORTES FINANCIEROS | J37: =IFERROR(VLOOKUP(MUESTREO_LABORAL_A2[[#This Row],[ACTIVIDAD]],'Lista Maestra'!$D$6:$F$190,3,0),"") -> REPORTERÍA | K37: =IFERROR(VLOOKUP(MUESTREO_LABORAL_A2[[#This Row],[ACTIVIDAD]],'Lista Maestra'!$D$6:$F$190,2,0),"") -> ELABORAR REPORTERÍA FINANCIERA MENSUAL PARA ELABORACIÓN DE BALANCES. | L37: CON ACTIVIDAD | N37: 0.44861111 | O37: 0.48819444 | P37: =IF(MUESTREO_LABORAL_A2[[#This Row],[TIEMPO INICIO]]="","",(MUESTREO_LABORAL_A2[[#This Row],[TIEMPO FIN]]-MUESTREO_LABORAL_A2[[#This Row],[TIEMPO INICIO]])*24) -> 0.95
B38: TSER | C38: CONTABILIDAD | D38: ANALISTA CONTABLE 2 EXPORTADORAS | E38: GERALDINE NAULA | F38: 45974 | I38: CREACIÓN Y ACTUALIZACIÓN DE ARTÍCULOS Y CUENTAS CONTABLES EN SAP | J38: =IFERROR(VLOOKUP(MUESTREO_LABORAL_A2[[#This Row],[ACTIVIDAD]],'Lista Maestra'!$D$6:$F$190,3,0),"") -> CREACIÓN DE ARTÍCULOS | K38: =IFERROR(VLOOKUP(MUESTREO_LABORAL_A2[[#This Row],[ACTIVIDAD]],'Lista Maestra'!$D$6:$F$190,2,0),"") -> SE REALIZA LA CREACIÓN Y ACTUALIZACIÓN DE ARTÍCULOS Y CUENTAS CONTABLES DE BIENES O SERVICIOS EN SAP, SEGÚN LOS REQUERIMIENTOS DE LAS DEMÁS ÁREAS. | L38: CON ACTIVIDAD | N38: 0.48819444 | O38: 0.49513889 | P38: =IF(MUESTREO_LABORAL_A2[[#This Row],[TIEMPO INICIO]]="","",(MUESTREO_LABORAL_A2[[#This Row],[TIEMPO FIN]]-MUESTREO_LABORAL_A2[[#This Row],[TIEMPO INICIO]])*24) -> 0.16666667
B39: TSER | C39: CONTABILIDAD | D39: ANALISTA CONTABLE 2 EXPORTADORAS | E39: GERALDINE NAULA | F39: 45974 | I39: ELABORACIÓN DE REPORTES FINANCIEROS | J39: =IFERROR(VLOOKUP(MUESTREO_LABORAL_A2[[#This Row],[ACTIVIDAD]],'Lista Maestra'!$D$6:$F$190,3,0),"") -> REPORTERÍA | K39: =IFERROR(VLOOKUP(MUESTREO_LABORAL_A2[[#This Row],[ACTIVIDAD]],'Lista Maestra'!$D$6:$F$190,2,0),"") -> ELABORAR REPORTERÍA FINANCIERA MENSUAL PARA ELABORACIÓN DE BALANCES. | L39: CON ACTIVIDAD | N39: 0.49513889 | O39: 0.52083333 | P39: =IF(MUESTREO_LABORAL_A2[[#This Row],[TIEMPO INICIO]]="","",(MUESTREO_LABORAL_A2[[#This Row],[TIEMPO FIN]]-MUESTREO_LABORAL_A2[[#This Row],[TIEMPO INICIO]])*24) -> 0.61666667
... B41: TSER | C41: CONTABILIDAD | D41: ANALISTA CONTABLE 2 EXPORTADORAS | E41: GERALDINE NAULA | F41: 45974 | I41: ELABORACIÓN DE REPORTES FINANCIEROS | J41: =IFERROR(VLOOKUP(MUESTREO_LABORAL_A2[[#This Row],[ACTIVIDAD]],'Lista Maestra'!$D$6:$F$190,3,0),"") -> REPORTERÍA | K41: =IFERROR(VLOOKUP(MUESTREO_LABORAL_A2[[#This Row],[ACTIVIDAD]],'Lista Maestra'!$D$6:$F$190,2,0),"") -> ELABORAR REPORTERÍA FINANCIERA MENSUAL PARA ELABORACIÓN DE BALANCES. | L41: CON ACTIVIDAD | N41: 0.5625 | O41: 0.625 | P41: =IF(MUESTREO_LABORAL_A2[[#This Row],[TIEMPO INICIO]]="","",(MUESTREO_LABORAL_A2[[#This Row],[TIEMPO FIN]]-MUESTREO_LABORAL_A2[[#This Row],[TIEMPO INICIO]])*24) -> 1.5
B42: TSER | C42: CONTABILIDAD | D42: ANALISTA CONTABLE 2 EXPORTADORAS | E42: GERALDINE NAULA | F42: 45975 | I42: EMISIÓN CERTIFICADOS DE EXPORTACIÓN | J42: =IFERROR(VLOOKUP(MUESTREO_LABORAL_A2[[#This Row],[ACTIVIDAD]],'Lista Maestra'!$D$6:$F$190,3,0),"") -> EMISIÓN CERTIFICADOS | K42: =IFERROR(VLOOKUP(MUESTREO_LABORAL_A2[[#This Row],[ACTIVIDAD]],'Lista Maestra'!$D$6:$F$190,2,0),"") -> ELABORACIÓN DE CERTIFICADOS PARA PRODUCTORES SEGÚN LOS MESES SOLICITADOS, INCLUYENDO EL DETALLE DE DAE, NÚMERO DE FACTURA DE VENTA, CANTIDAD DE CAJAS EXPORTADAS, FECHA DE CIERRE DE LAS DAE, VALOR TOTAL EN USD Y FACTURA DE COMPRA DEL PROVEEDOR. | L42: CON ACTIVIDAD | N42: 0.35416667 | O42: 0.4 | P42: =IF(MUESTREO_LABORAL_A2[[#This Row],[TIEMPO INICIO]]="","",(MUESTREO_LABORAL_A2[[#This Row],[TIEMPO FIN]]-MUESTREO_LABORAL_A2[[#This Row],[TIEMPO INICIO]])*24) -> 1.1 | Q42: Hoy revisaré el flujo de multinational eso es un excel compartido que tenemos con juanjo de comercial y el en este excel registra todas las facturas de proveedores que son emitidas a multinational como sabes multinational es de USA entonces no esta en el portal del SRI Por ese motivo se creo este flujo, para tener un mayor control ese lo usamos juan, angelo y yo juanjo llena el excel, yo lo reviso y hago los ingresos de fc correspondiente y angelo mira lo que esta ingresado y paga asi nos manejamos
B43: TSER | C43: CONTABILIDAD | D43: ANALISTA CONTABLE 2 EXPORTADORAS | E43: GERALDINE NAULA | F43: 45975 | I43: FACTURACIÓN DDP BANANO COSTCO | J43: =IFERROR(VLOOKUP(MUESTREO_LABORAL_A2[[#This Row],[ACTIVIDAD]],'Lista Maestra'!$D$6:$F$190,3,0),"") -> FACTURACIÓN A CLIENTES | K43: =IFERROR(VLOOKUP(MUESTREO_LABORAL_A2[[#This Row],[ACTIVIDAD]],'Lista Maestra'!$D$6:$F$190,2,0),"") -> ELABORACIÓN SEMANAL DE FACTURAS DE BANANO PARA CLIENTES INTERNACIONALES EN MULTINATIONAL, TRABAJANDO CON LOS REPORTES DE TRÁMITES DE LA SEMANA, DETALLE DE CONSOLIDACIÓN EN FTL Y B/LS, FACTURACIÓN SE REALIZA 21 DÍAS DESPUES DEL ZARPE DE LA CARGA | L43: CON ACTIVIDAD | N43: 0.4 | O43: 0.45347222 | P43: =IF(MUESTREO_LABORAL_A2[[#This Row],[TIEMPO INICIO]]="","",(MUESTREO_LABORAL_A2[[#This Row],[TIEMPO FIN]]-MUESTREO_LABORAL_A2[[#This Row],[TIEMPO INICIO]])*24) -> 1.2833333
B44: TSER | C44: CONTABILIDAD | D44: ANALISTA CONTABLE 2 EXPORTADORAS | E44: GERALDINE NAULA | F44: 45975 | I44: GESTIÓN DE REPOSICIÓN Y CONTROL DE CAJA CHICA EL CARMEN Y EL PAN | J44: =IFERROR(VLOOKUP(MUESTREO_LABORAL_A2[[#This Row],[ACTIVIDAD]],'Lista Maestra'!$D$6:$F$190,3,0),"") -> CONTROL DE CAJA CHICA | K44: =IFERROR(VLOOKUP(MUESTREO_LABORAL_A2[[#This Row],[ACTIVIDAD]],'Lista Maestra'!$D$6:$F$190,2,0),"") -> SE EJECUTA LA GESTIÓN DE REPOSICIÓN Y CONTROL DE CAJA CHICA, MEDIANTE LA REVISIÓN DE COMPROBANTES DE GASTO, VALIDACIÓN DE SOPORTES Y REGISTRO CONTABLE DE LOS MOVIMIENTOS EFECTUADOS. SE VERIFICA QUE LOS GASTOS SE ENCUENTREN DENTRO DE LAS POLÍTICAS INTERNAS Y SE PREPARA LA SOLICITUD DE REPOSICIÓN CORRESPONDIENTE. | L44: CON ACTIVIDAD | N44: 0.45347222 | O44: 0.52083333 | P44: =IF(MUESTREO_LABORAL_A2[[#This Row],[TIEMPO INICIO]]="","",(MUESTREO_LABORAL_A2[[#This Row],[TIEMPO FIN]]-MUESTREO_LABORAL_A2[[#This Row],[TIEMPO INICIO]])*24) -> 1.6166667
B45: TSER | C45: CONTABILIDAD | D45: ANALISTA CONTABLE 2 EXPORTADORAS | E45: GERALDINE NAULA | F45: 45975 | I45: ALIMENTACIÓN | J45: =IFERROR(VLOOKUP(MUESTREO_LABORAL_A2[[#This Row],[ACTIVIDAD]],'Lista Maestra'!$D$6:$F$190,3,0),"") -> ALIMENTACIÓN | K45: =IFERROR(VLOOKUP(MUESTREO_LABORAL_A2[[#This Row],[ACTIVIDAD]],'Lista Maestra'!$D$6:$F$190,2,0),"") -> ALIMENTARSE | L45: ALIMENTACIÓN | N45: 0.52083333 | O45: 0.5625 | P45: =IF(MUESTREO_LABORAL_A2[[#This Row],[TIEMPO INICIO]]="","",(MUESTREO_LABORAL_A2[[#This Row],[TIEMPO FIN]]-MUESTREO_LABORAL_A2[[#This Row],[TIEMPO INICIO]])*24) -> 1
B46: TSER | C46: CONTABILIDAD | D46: ANALISTA CONTABLE 2 EXPORTADORAS | E46: GERALDINE NAULA | F46: 45975 | I46: EMISIÓN CERTIFICADOS DE EXPORTACIÓN | J46: =IFERROR(VLOOKUP(MUESTREO_LABORAL_A2[[#This Row],[ACTIVIDAD]],'Lista Maestra'!$D$6:$F$190,3,0),"") -> EMISIÓN CERTIFICADOS | K46: =IFERROR(VLOOKUP(MUESTREO_LABORAL_A2[[#This Row],[ACTIVIDAD]],'Lista Maestra'!$D$6:$F$190,2,0),"") -> ELABORACIÓN DE CERTIFICADOS PARA PRODUCTORES SEGÚN LOS MESES SOLICITADOS, INCLUYENDO EL DETALLE DE DAE, NÚMERO DE FACTURA DE VENTA, CANTIDAD DE CAJAS EXPORTADAS, FECHA DE CIERRE DE LAS DAE, VALOR TOTAL EN USD Y FACTURA DE COMPRA DEL PROVEEDOR. | L46: CON ACTIVIDAD | N46: 0.5625 | O46: 0.60416667 | P46: =IF(MUESTREO_LABORAL_A2[[#This Row],[TIEMPO INICIO]]="","",(MUESTREO_LABORAL_A2[[#This Row],[TIEMPO FIN]]-MUESTREO_LABORAL_A2[[#This Row],[TIEMPO INICIO]])*24) -> 1 | Q46: ya me llegaron las fc de tfe a mlc por la venta de fruta
B47: TSER | C47: CONTABILIDAD | D47: ANALISTA CONTABLE 2 EXPORTADORAS | E47: GERALDINE NAULA | F47: 45975 | I47: GESTIÓN CONTABLE Y CLASIFICACIÓN DE CUENTAS FINANCIERAS | J47: =IFERROR(VLOOKUP(MUESTREO_LABORAL_A2[[#This Row],[ACTIVIDAD]],'Lista Maestra'!$D$6:$F$190,3,0),"") -> ANÁLISIS DE CUENTAS | K47: =IFERROR(VLOOKUP(MUESTREO_LABORAL_A2[[#This Row],[ACTIVIDAD]],'Lista Maestra'!$D$6:$F$190,2,0),"") -> SE REALIZA LA GESTIÓN CONTABLE Y CLASIFICACIÓN DE CUENTAS FINANCIERAS, MEDIANTE LA REVISIÓN, ANÁLISIS Y REGISTRO DE LOS MOVIMIENTOS CONTABLES EN EL SISTEMA. SE CLASIFICAN LAS TRANSACCIONES SEGÚN SU NATURALEZA (ACTIVOS, PASIVOS, INGRESOS Y GASTOS) | L47: CON ACTIVIDAD | N47: 0.60416667 | O47: 0.625 | P47: =IF(MUESTREO_LABORAL_A2[[#This Row],[TIEMPO INICIO]]="","",(MUESTREO_LABORAL_A2[[#This Row],[TIEMPO FIN]]-MUESTREO_LABORAL_A2[[#This Row],[TIEMPO INICIO]])*24) -> 0.5
B48: SMART | C48: PLANIFICACIÓN | D48: PLANIFICADOR | E48: BRANCO DÁVILA | F48: 45978 | I48: PROGRAMACIÓN DE TRANSPORTE | J48: =IFERROR(VLOOKUP(MUESTREO_LABORAL_A2[[#This Row],[ACTIVIDAD]],'Lista Maestra'!$D$6:$F$190,3,0),"") -> RECEPCIÓN DE SOLICITUD DE TRANSPORTE | K48: =IFERROR(VLOOKUP(MUESTREO_LABORAL_A2[[#This Row],[ACTIVIDAD]],'Lista Maestra'!$D$6:$F$190,2,0),"") -> CUADRE DE VEHÍCULOS EN BASE A LOS CORTES QUE ESTÁN PROGRAMADOS. REVISIÓN SOLICITUD DE OMARSA REVISIÓN LISTADO DE PROVEEDORES DE TRANSPORTE. REVISIÓN ASIGNACIÓN DE CHOFERES TANTO PROVEEDORES DE TRANSPORTE COMO PROVEEDORES PROPIOS. GENERACIÓN DE PLANIFICACIÓN DE TRANSPORTE DEL CORTE DEL MARTES. PLANIFICACIÓN DE BANANO REVISA EN FTL Y SE LO UBICA EN LA BASE DE TRANSPORTE. | L48: CON ACTIVIDAD | N48: 0.35416667 | O48: 0.46458333 | P48: =IF(MUESTREO_LABORAL_A2[[#This Row],[TIEMPO INICIO]]="","",(MUESTREO_LABORAL_A2[[#This Row],[TIEMPO FIN]]-MUESTREO_LABORAL_A2[[#This Row],[TIEMPO INICIO]])*24) -> 2.65 | Q48: Tuvo reunión con Abelardo, pero, no me avisó en qué momento se reunió con él, por tal motivo, en este tiempo tiene asociado lo que le tomó la reunión con Abelardo.
B49: SMART | C49: PLANIFICACIÓN | D49: PLANIFICADOR | E49: BRANCO DÁVILA | F49: 45978 | I49: REVISIÓN PLANIFICACIÓN DE PIÑAS | J49: =IFERROR(VLOOKUP(MUESTREO_LABORAL_A2[[#This Row],[ACTIVIDAD]],'Lista Maestra'!$D$6:$F$190,3,0),"") -> PLANIFICACIÓN | K49: =IFERROR(VLOOKUP(MUESTREO_LABORAL_A2[[#This Row],[ACTIVIDAD]],'Lista Maestra'!$D$6:$F$190,2,0),"") -> 0 | L49: CON ACTIVIDAD | N49: 0.46458333 | O49: 0.47013889 | P49: =IF(MUESTREO_LABORAL_A2[[#This Row],[TIEMPO INICIO]]="","",(MUESTREO_LABORAL_A2[[#This Row],[TIEMPO FIN]]-MUESTREO_LABORAL_A2[[#This Row],[TIEMPO INICIO]])*24) -> 0.13333333
B50: SMART | C50: PLANIFICACIÓN | D50: PLANIFICADOR | E50: BRANCO DÁVILA | F50: 45978 | I50: REVISIÓN PROGRAMACIÓN PLÁTANO | J50: =IFERROR(VLOOKUP(MUESTREO_LABORAL_A2[[#This Row],[ACTIVIDAD]],'Lista Maestra'!$D$6:$F$190,3,0),"") -> PLANIFICACIÓN | K50: =IFERROR(VLOOKUP(MUESTREO_LABORAL_A2[[#This Row],[ACTIVIDAD]],'Lista Maestra'!$D$6:$F$190,2,0),"") -> 0 | L50: CON ACTIVIDAD | N50: 0.47013889 | O50: 0.47361111 | P50: =IF(MUESTREO_LABORAL_A2[[#This Row],[TIEMPO INICIO]]="","",(MUESTREO_LABORAL_A2[[#This Row],[TIEMPO FIN]]-MUESTREO_LABORAL_A2[[#This Row],[TIEMPO INICIO]])*24) -> 0.083333333
B51: SMART | C51: PLANIFICACIÓN | D51: PLANIFICADOR | E51: BRANCO DÁVILA | F51: 45978 | I51: REVISIÓN PROGRAMACIÓN CACAO | J51: =IFERROR(VLOOKUP(MUESTREO_LABORAL_A2[[#This Row],[ACTIVIDAD]],'Lista Maestra'!$D$6:$F$190,3,0),"") -> PLANIFICACIÓN | K51: =IFERROR(VLOOKUP(MUESTREO_LABORAL_A2[[#This Row],[ACTIVIDAD]],'Lista Maestra'!$D$6:$F$190,2,0),"") -> 0 | L51: CON ACTIVIDAD | N51: 0.47361111 | O51: 0.47916667 | P51: =IF(MUESTREO_LABORAL_A2[[#This Row],[TIEMPO INICIO]]="","",(MUESTREO_LABORAL_A2[[#This Row],[TIEMPO FIN]]-MUESTREO_LABORAL_A2[[#This Row],[TIEMPO INICIO]])*24) -> 0.13333333
B52: SMART | C52: PLANIFICACIÓN | D52: PLANIFICADOR | E52: BRANCO DÁVILA | F52: 45978 | I52: PROGRAMACIÓN DE TRANSPORTE | J52: =IFERROR(VLOOKUP(MUESTREO_LABORAL_A2[[#This Row],[ACTIVIDAD]],'Lista Maestra'!$D$6:$F$190,3,0),"") -> RECEPCIÓN DE SOLICITUD DE TRANSPORTE | K52: =IFERROR(VLOOKUP(MUESTREO_LABORAL_A2[[#This Row],[ACTIVIDAD]],'Lista Maestra'!$D$6:$F$190,2,0),"") -> CUADRE DE VEHÍCULOS EN BASE A LOS CORTES QUE ESTÁN PROGRAMADOS. REVISIÓN SOLICITUD DE OMARSA REVISIÓN LISTADO DE PROVEEDORES DE TRANSPORTE. REVISIÓN ASIGNACIÓN DE CHOFERES TANTO PROVEEDORES DE TRANSPORTE COMO PROVEEDORES PROPIOS. GENERACIÓN DE PLANIFICACIÓN DE TRANSPORTE DEL CORTE DEL MARTES. PLANIFICACIÓN DE BANANO REVISA EN FTL Y SE LO UBICA EN LA BASE DE TRANSPORTE. | L52: CON ACTIVIDAD | N52: 0.47916667 | O52: 0.53333333 | P52: =IF(MUESTREO_LABORAL_A2[[#This Row],[TIEMPO INICIO]]="","",(MUESTREO_LABORAL_A2[[#This Row],[TIEMPO FIN]]-MUESTREO_LABORAL_A2[[#This Row],[TIEMPO INICIO]])*24) -> 1.3
B53: SMART | C53: PLANIFICACIÓN | D53: PLANIFICADOR | E53: BRANCO DÁVILA | F53: 45978 | I53: ALIMENTACIÓN | J53: =IFERROR(VLOOKUP(MUESTREO_LABORAL_A2[[#This Row],[ACTIVIDAD]],'Lista Maestra'!$D$6:$F$190,3,0),"") -> ALIMENTACIÓN | K53: =IFERROR(VLOOKUP(MUESTREO_LABORAL_A2[[#This Row],[ACTIVIDAD]],'Lista Maestra'!$D$6:$F$190,2,0),"") -> ALIMENTARSE | L53: ALIMENTACIÓN | N53: 0.53333333 | O53: 0.55555556 | P53: =IF(MUESTREO_LABORAL_A2[[#This Row],[TIEMPO INICIO]]="","",(MUESTREO_LABORAL_A2[[#This Row],[TIEMPO FIN]]-MUESTREO_LABORAL_A2[[#This Row],[TIEMPO INICIO]])*24) -> 0.53333333 | Q53: espero confirmacion de los transportista
B54: SMART | C54: PLANIFICACIÓN | D54: PLANIFICADOR | E54: BRANCO DÁVILA | F54: 45978 | I54: PROGRAMACIÓN DE TRANSPORTE | J54: =IFERROR(VLOOKUP(MUESTREO_LABORAL_A2[[#This Row],[ACTIVIDAD]],'Lista Maestra'!$D$6:$F$190,3,0),"") -> RECEPCIÓN DE SOLICITUD DE TRANSPORTE | K54: =IFERROR(VLOOKUP(MUESTREO_LABORAL_A2[[#This Row],[ACTIVIDAD]],'Lista Maestra'!$D$6:$F$190,2,0),"") -> CUADRE DE VEHÍCULOS EN BASE A LOS CORTES QUE ESTÁN PROGRAMADOS. REVISIÓN SOLICITUD DE OMARSA REVISIÓN LISTADO DE PROVEEDORES DE TRANSPORTE. REVISIÓN ASIGNACIÓN DE CHOFERES TANTO PROVEEDORES DE TRANSPORTE COMO PROVEEDORES PROPIOS. GENERACIÓN DE PLANIFICACIÓN DE TRANSPORTE DEL CORTE DEL MARTES. PLANIFICACIÓN DE BANANO REVISA EN FTL Y SE LO UBICA EN LA BASE DE TRANSPORTE. | L54: CON ACTIVIDAD | N54: 0.55555556 | O54: 0.57222222 | P54: =IF(MUESTREO_LABORAL_A2[[#This Row],[TIEMPO INICIO]]="","",(MUESTREO_LABORAL_A2[[#This Row],[TIEMPO FIN]]-MUESTREO_LABORAL_A2[[#This Row],[TIEMPO INICIO]])*24) -> 0.4 | Q54: Espero confirmacion de Victor si se mantienen lo programado en ftl con dos casos en fincas. Hasta eso voy a parar la programacion de transporte.
B55: SMART | C55: PLANIFICACIÓN | D55: PLANIFICADOR | E55: BRANCO DÁVILA | F55: 45978 | I55: REVISIÓN KILOMETRAJE INICIO DE SEMANA | J55: =IFERROR(VLOOKUP(MUESTREO_LABORAL_A2[[#This Row],[ACTIVIDAD]],'Lista Maestra'!$D$6:$F$190,3,0),"") -> CONSOLIDACIÓN | K55: =IFERROR(VLOOKUP(MUESTREO_LABORAL_A2[[#This Row],[ACTIVIDAD]],'Lista Maestra'!$D$6:$F$190,2,0),"") -> REVISIÓN KILOMETRAJE DE LOS VEHÍCULOS DE SMART DE LA SEMANA ANTERIOR. | L55: CON ACTIVIDAD | N55: 0.57222222 | O55: 0.61388889 | P55: =IF(MUESTREO_LABORAL_A2[[#This Row],[TIEMPO INICIO]]="","",(MUESTREO_LABORAL_A2[[#This Row],[TIEMPO FIN]]-MUESTREO_LABORAL_A2[[#This Row],[TIEMPO INICIO]])*24) -> 1 | Q55: culminado la recopilacion de informacion de los kilometrajes de la flota propia.
B56: SMART | C56: PLANIFICACIÓN | D56: PLANIFICADOR | E56: BRANCO DÁVILA | F56: 45978 | I56: PROGRAMACIÓN DE TRANSPORTE | J56: =IFERROR(VLOOKUP(MUESTREO_LABORAL_A2[[#This Row],[ACTIVIDAD]],'Lista Maestra'!$D$6:$F$190,3,0),"") -> RECEPCIÓN DE SOLICITUD DE TRANSPORTE | K56: =IFERROR(VLOOKUP(MUESTREO_LABORAL_A2[[#This Row],[ACTIVIDAD]],'Lista Maestra'!$D$6:$F$190,2,0),"") -> CUADRE DE VEHÍCULOS EN BASE A LOS CORTES QUE ESTÁN PROGRAMADOS. REVISIÓN SOLICITUD DE OMARSA REVISIÓN LISTADO DE PROVEEDORES DE TRANSPORTE. REVISIÓN ASIGNACIÓN DE CHOFERES TANTO PROVEEDORES DE TRANSPORTE COMO PROVEEDORES PROPIOS. GENERACIÓN DE PLANIFICACIÓN DE TRANSPORTE DEL CORTE DEL MARTES. PLANIFICACIÓN DE BANANO REVISA EN FTL Y SE LO UBICA EN LA BASE DE TRANSPORTE. | L56: CON ACTIVIDAD | N56: 0.61388889 | O56: 0.68333333 | P56: =IF(MUESTREO_LABORAL_A2[[#This Row],[TIEMPO INICIO]]="","",(MUESTREO_LABORAL_A2[[#This Row],[TIEMPO FIN]]-MUESTREO_LABORAL_A2[[#This Row],[TIEMPO INICIO]])*24) -> 1.6666667 | Q56: voy a volver a la revisar la programacion, ya que en el grupo de fallos reportaron cambios pasado los viajes a los proveedores de transporte finalizado
B57: SMART | C57: PLANIFICACIÓN | D57: PLANIFICADOR | E57: BRANCO DÁVILA | F57: 45978 | I57: REVISIÓN PROGRAMACIÓN OPERACIONES | J57: =IFERROR(VLOOKUP(MUESTREO_LABORAL_A2[[#This Row],[ACTIVIDAD]],'Lista Maestra'!$D$6:$F$190,3,0),"") -> PLANIFICACIÓN | K57: =IFERROR(VLOOKUP(MUESTREO_LABORAL_A2[[#This Row],[ACTIVIDAD]],'Lista Maestra'!$D$6:$F$190,2,0),"") -> REVISIÓN DE CAMBIOS. LISTA DE ACOPIOS. | L57: CON ACTIVIDAD | N57: 0.68333333 | O57: 0.69027778 | P57: =IF(MUESTREO_LABORAL_A2[[#This Row],[TIEMPO INICIO]]="","",(MUESTREO_LABORAL_A2[[#This Row],[TIEMPO FIN]]-MUESTREO_LABORAL_A2[[#This Row],[TIEMPO INICIO]])*24) -> 0.16666667
B58: SMART | C58: PLANIFICACIÓN | D58: PLANIFICADOR | E58: BRANCO DÁVILA | F58: 45979 | I58: REVISIÓN PROGRAMACIÓN BANANO | J58: =IFERROR(VLOOKUP(MUESTREO_LABORAL_A2[[#This Row],[ACTIVIDAD]],'Lista Maestra'!$D$6:$F$190,3,0),"") -> PLANIFICACIÓN | K58: =IFERROR(VLOOKUP(MUESTREO_LABORAL_A2[[#This Row],[ACTIVIDAD]],'Lista Maestra'!$D$6:$F$190,2,0),"") -> 0 | L58: CON ACTIVIDAD | N58: 0.35416667 | O58: 0.42569444 | P58: =IF(MUESTREO_LABORAL_A2[[#This Row],[TIEMPO INICIO]]="","",(MUESTREO_LABORAL_A2[[#This Row],[TIEMPO FIN]]-MUESTREO_LABORAL_A2[[#This Row],[TIEMPO INICIO]])*24) -> 1.7166667 | Q58: banano termine de acoplar lo de ftl al programa de transporte. Aqui espero confirmacion de logistica sobre el tipo de ctr, carreta o camion que vayan a procesar en fincas puntuales
B59: SMART | C59: PLANIFICACIÓN | D59: PLANIFICADOR | E59: BRANCO DÁVILA | F59: 45979 | I59: REVISIÓN PLANIFICACIÓN DE PIÑAS | J59: =IFERROR(VLOOKUP(MUESTREO_LABORAL_A2[[#This Row],[ACTIVIDAD]],'Lista Maestra'!$D$6:$F$190,3,0),"") -> PLANIFICACIÓN | K59: =IFERROR(VLOOKUP(MUESTREO_LABORAL_A2[[#This Row],[ACTIVIDAD]],'Lista Maestra'!$D$6:$F$190,2,0),"") -> 0 | L59: CON ACTIVIDAD | N59: 0.42569444 | O59: 0.4375 | P59: =IF(MUESTREO_LABORAL_A2[[#This Row],[TIEMPO INICIO]]="","",(MUESTREO_LABORAL_A2[[#This Row],[TIEMPO FIN]]-MUESTREO_LABORAL_A2[[#This Row],[TIEMPO INICIO]])*24) -> 0.28333333 | Q59: Lo de la planificación de piñas, tambien lo hago diario por los cambios que realizan los clientes. El programa que ellos pasan no siempre se cumple. Por lo que es necesario revisar diario para evitar que algun ctr no se retire o envie. lo que mencionaba sobre piñas que hay que programar por dia ya hay un cambio
B60: SMART | C60: PLANIFICACIÓN | D60: PLANIFICADOR | E60: BRANCO DÁVILA | F60: 45979 | I60: PROGRAMACIÓN DE OLAM | J60: =IFERROR(VLOOKUP(MUESTREO_LABORAL_A2[[#This Row],[ACTIVIDAD]],'Lista Maestra'!$D$6:$F$190,3,0),"") -> PLANIFICACIÓN | K60: =IFERROR(VLOOKUP(MUESTREO_LABORAL_A2[[#This Row],[ACTIVIDAD]],'Lista Maestra'!$D$6:$F$190,2,0),"") -> 0 | L60: CON ACTIVIDAD | N60: 0.4375 | O60: 0.44375 | P60: =IF(MUESTREO_LABORAL_A2[[#This Row],[TIEMPO INICIO]]="","",(MUESTREO_LABORAL_A2[[#This Row],[TIEMPO FIN]]-MUESTREO_LABORAL_A2[[#This Row],[TIEMPO INICIO]])*24) -> 0.15
B61: SMART | C61: PLANIFICACIÓN | D61: PLANIFICADOR | E61: BRANCO DÁVILA | F61: 45979 | I61: PROGRAMACIÓN DE TRANSPORTE | J61: =IFERROR(VLOOKUP(MUESTREO_LABORAL_A2[[#This Row],[ACTIVIDAD]],'Lista Maestra'!$D$6:$F$190,3,0),"") -> RECEPCIÓN DE SOLICITUD DE TRANSPORTE | K61: =IFERROR(VLOOKUP(MUESTREO_LABORAL_A2[[#This Row],[ACTIVIDAD]],'Lista Maestra'!$D$6:$F$190,2,0),"") -> CUADRE DE VEHÍCULOS EN BASE A LOS CORTES QUE ESTÁN PROGRAMADOS. REVISIÓN SOLICITUD DE OMARSA REVISIÓN LISTADO DE PROVEEDORES DE TRANSPORTE. REVISIÓN ASIGNACIÓN DE CHOFERES TANTO PROVEEDORES DE TRANSPORTE COMO PROVEEDORES PROPIOS. GENERACIÓN DE PLANIFICACIÓN DE TRANSPORTE DEL CORTE DEL MARTES. PLANIFICACIÓN DE BANANO REVISA EN FTL Y SE LO UBICA EN LA BASE DE TRANSPORTE. | L61: CON ACTIVIDAD | N61: 0.44375 | O61: 0.51944444 | P61: =IF(MUESTREO_LABORAL_A2[[#This Row],[TIEMPO INICIO]]="","",(MUESTREO_LABORAL_A2[[#This Row],[TIEMPO FIN]]-MUESTREO_LABORAL_A2[[#This Row],[TIEMPO INICIO]])*24) -> 1.8166667 | Q61: si, luego de la programacion ( Realizar el archivo) debo asignar, es decir revisar cantidades de vehiculos por transportista en funcion de la cantidad de viajes es la parte que mas toma tiempo, ya que los proveedores terminan fallando las cantidades acordadas. El sabado laboro tambien, ahi me pongo a cuadrar cantidad de carros a usar por dia, esto es preliminar. En el transcurso del dia a requerir si hay cambios o se mantiene mantengo comunicacion con el transportista
B62: SMART | C62: PLANIFICACIÓN | D62: PLANIFICADOR | E62: BRANCO DÁVILA | F62: 45979 | I62: NECESIDADES BIOLÓGICAS | J62: =IFERROR(VLOOKUP(MUESTREO_LABORAL_A2[[#This Row],[ACTIVIDAD]],'Lista Maestra'!$D$6:$F$190,3,0),"") -> NECESIDADES BIOLÓGICAS | K62: =IFERROR(VLOOKUP(MUESTREO_LABORAL_A2[[#This Row],[ACTIVIDAD]],'Lista Maestra'!$D$6:$F$190,2,0),"") -> PROCESO DE MICCIÓN Y AGREGADOS | N62: 0.51944444 | O62: 0.52777778 | P62: =IF(MUESTREO_LABORAL_A2[[#This Row],[TIEMPO INICIO]]="","",(MUESTREO_LABORAL_A2[[#This Row],[TIEMPO FIN]]-MUESTREO_LABORAL_A2[[#This Row],[TIEMPO INICIO]])*24) -> 0.2 | Q62: Ahora voy al baño. Regreso en 15 min. Avanzo luego almorzar y retomo. la siguiente actividad es revisar Kilometrajes de inicio de semana. Ayer realize kilometrajes de finalizacion es decir, como los vehiculos trabajan hasta los sabados y se desocupan recien el domingo madrugada
B63: SMART | C63: PLANIFICACIÓN | D63: PLANIFICADOR | E63: BRANCO DÁVILA | F63: 45979 | I63: ALIMENTACIÓN | J63: =IFERROR(VLOOKUP(MUESTREO_LABORAL_A2[[#This Row],[ACTIVIDAD]],'Lista Maestra'!$D$6:$F$190,3,0),"") -> ALIMENTACIÓN | K63: =IFERROR(VLOOKUP(MUESTREO_LABORAL_A2[[#This Row],[ACTIVIDAD]],'Lista Maestra'!$D$6:$F$190,2,0),"") -> ALIMENTARSE | N63: 0.52777778 | O63: 0.54930556 | P63: =IF(MUESTREO_LABORAL_A2[[#This Row],[TIEMPO INICIO]]="","",(MUESTREO_LABORAL_A2[[#This Row],[TIEMPO FIN]]-MUESTREO_LABORAL_A2[[#This Row],[TIEMPO INICIO]])*24) -> 0.51666667
B64: SMART | C64: PLANIFICACIÓN | D64: PLANIFICADOR | E64: BRANCO DÁVILA | F64: 45979 | I64: ELABORACIÓN KILOMETRAJE FINALIZACIÓN | J64: =IFERROR(VLOOKUP(MUESTREO_LABORAL_A2[[#This Row],[ACTIVIDAD]],'Lista Maestra'!$D$6:$F$190,3,0),"") -> CONSOLIDACIÓN | K64: =IFERROR(VLOOKUP(MUESTREO_LABORAL_A2[[#This Row],[ACTIVIDAD]],'Lista Maestra'!$D$6:$F$190,2,0),"") -> 0 | L64: CON ACTIVIDAD | N64: 0.54930556 | O64: 0.59097222 | P64: =IF(MUESTREO_LABORAL_A2[[#This Row],[TIEMPO INICIO]]="","",(MUESTREO_LABORAL_A2[[#This Row],[TIEMPO FIN]]-MUESTREO_LABORAL_A2[[#This Row],[TIEMPO INICIO]])*24) -> 1 | Q64: Ahora mismo, del grupo de base de datos, alli reportan los choferes kilometrajes del vehiculo y chasis inicio frecuentemente los martes como inicio de semana ya que los lunes al no haber volumen para todos los vehiculos viajan una cierta cantidad. Martes ya viajan todos. por ende ya la informacion esta completa para recopilar. en este momento culmine, pendiente que un chofer envie el dato del kilometraje del chasis por ahora cierro.
B65: SMART | C65: PLANIFICACIÓN | D65: PLANIFICADOR | E65: BRANCO DÁVILA | F65: 45979 | I65: RENOVACIÓN DE DOCUMENTOS DE VEHÍCULOS EN DP WORLD | J65: =IFERROR(VLOOKUP(MUESTREO_LABORAL_A2[[#This Row],[ACTIVIDAD]],'Lista Maestra'!$D$6:$F$190,3,0),"") | K65: =IFERROR(VLOOKUP(MUESTREO_LABORAL_A2[[#This Row],[ACTIVIDAD]],'Lista Maestra'!$D$6:$F$190,2,0),"") | L65: CON ACTIVIDAD | N65: 0.59097222 | O65: 0.61597222 | P65: =IF(MUESTREO_LABORAL_A2[[#This Row],[TIEMPO INICIO]]="","",(MUESTREO_LABORAL_A2[[#This Row],[TIEMPO FIN]]-MUESTREO_LABORAL_A2[[#This Row],[TIEMPO INICIO]])*24) -> 0.6 | Q65: Avanzo a realizar renovacion de documentos de vehiculos en dp world luego contecon Lo que voy hacer es solicitudes para actualizacion de documentos de 3 cabezales esta por vencer la revision tecnica vehicular pero ya tengo las ordenes por recaudacion lo subo como prorroga hasta que emita atm los certificados ahora me encuentro revisando en la base los documentos que me los enviaron
B66: SMART | C66: PLANIFICACIÓN | D66: PLANIFICADOR | E66: BRANCO DÁVILA | F66: 45979 | I66: REVISIÓN PROGRAMACIÓN EN FTL | J66: =IFERROR(VLOOKUP(MUESTREO_LABORAL_A2[[#This Row],[ACTIVIDAD]],'Lista Maestra'!$D$6:$F$190,3,0),"") -> PLANIFICACIÓN | K66: =IFERROR(VLOOKUP(MUESTREO_LABORAL_A2[[#This Row],[ACTIVIDAD]],'Lista Maestra'!$D$6:$F$190,2,0),"") -> REVISAR SI HAY ALGÚN CAMBIO QUE HAYA HECHO TROPICAL. TODO CAMBIO DEBE REPORTARSE EN EL GRUPO DE FALLAS VÍA WHATSAPP. | L66: CON ACTIVIDAD | N66: 0.61597222 | O66: 0.63680556 | P66: =IF(MUESTREO_LABORAL_A2[[#This Row],[TIEMPO INICIO]]="","",(MUESTREO_LABORAL_A2[[#This Row],[TIEMPO FIN]]-MUESTREO_LABORAL_A2[[#This Row],[TIEMPO INICIO]])*24) -> 0.5 | Q66: hasta la mañana habia una programacion diferente en asopaop. Ya hay cambios que no han notificado en el grupo de fallas por eso en este horario debo revisar grupo de fallas no hay reporte
B67: SMART | C67: PLANIFICACIÓN | D67: PLANIFICADOR | E67: BRANCO DÁVILA | F67: 45979 | I67: PROGRAMACIÓN DE TRANSPORTE | J67: =IFERROR(VLOOKUP(MUESTREO_LABORAL_A2[[#This Row],[ACTIVIDAD]],'Lista Maestra'!$D$6:$F$190,3,0),"") -> RECEPCIÓN DE SOLICITUD DE TRANSPORTE | K67: =IFERROR(VLOOKUP(MUESTREO_LABORAL_A2[[#This Row],[ACTIVIDAD]],'Lista Maestra'!$D$6:$F$190,2,0),"") -> CUADRE DE VEHÍCULOS EN BASE A LOS CORTES QUE ESTÁN PROGRAMADOS. REVISIÓN SOLICITUD DE OMARSA REVISIÓN LISTADO DE PROVEEDORES DE TRANSPORTE. REVISIÓN ASIGNACIÓN DE CHOFERES TANTO PROVEEDORES DE TRANSPORTE COMO PROVEEDORES PROPIOS. GENERACIÓN DE PLANIFICACIÓN DE TRANSPORTE DEL CORTE DEL MARTES. PLANIFICACIÓN DE BANANO REVISA EN FTL Y SE LO UBICA EN LA BASE DE TRANSPORTE. | L67: CON ACTIVIDAD | N67: 0.63680556 | O67: 0.68888889 | P67: =IF(MUESTREO_LABORAL_A2[[#This Row],[TIEMPO INICIO]]="","",(MUESTREO_LABORAL_A2[[#This Row],[TIEMPO FIN]]-MUESTREO_LABORAL_A2[[#This Row],[TIEMPO INICIO]])*24) -> 1.25 | Q67: procedo a revisar choferes habilitados en puertos asignados. le voy a pasar el programa a Logistica para la revision luego de ellos me pongo a revisar el detalle de reserva vs programacion para verificar acopios que deben pedirme para separar los carros y verificar consumo de bks de semana el detalle de reserva lo pasa comex, en base a eso se revisa. Tambien incluir envio de viajes a los choferes que no manejan un coordinador.
B68: SMART | C68: PLANIFICACIÓN | D68: PLANIFICADOR | E68: BRANCO DÁVILA | F68: 45980 | I68: AJUSTE DE PROGRAMACIÓN DE DESPACHO | J68: =IFERROR(VLOOKUP(MUESTREO_LABORAL_A2[[#This Row],[ACTIVIDAD]],'Lista Maestra'!$D$6:$F$190,3,0),"") -> PLANIFICACIÓN | K68: =IFERROR(VLOOKUP(MUESTREO_LABORAL_A2[[#This Row],[ACTIVIDAD]],'Lista Maestra'!$D$6:$F$190,2,0),"") -> CON RESPECTO AL DÍA ANTERIOR. | L68: CON ACTIVIDAD | N68: 0.35416667 | O68: 0.40625 | P68: =IF(MUESTREO_LABORAL_A2[[#This Row],[TIEMPO INICIO]]="","",(MUESTREO_LABORAL_A2[[#This Row],[TIEMPO FIN]]-MUESTREO_LABORAL_A2[[#This Row],[TIEMPO INICIO]])*24) -> 1.25 | Q68: del corte del miercoles hay carros que aun no culminan los viajes de ayer y estan de regreso
B69: SMART | C69: PLANIFICACIÓN | D69: PLANIFICADOR | E69: BRANCO DÁVILA | F69: 45980 | I69: PROGRAMACIÓN DE PLÁTANO, PIÑAS Y CACAO | J69: =IFERROR(VLOOKUP(MUESTREO_LABORAL_A2[[#This Row],[ACTIVIDAD]],'Lista Maestra'!$D$6:$F$190,3,0),"") -> PLANIFICACIÓN | K69: =IFERROR(VLOOKUP(MUESTREO_LABORAL_A2[[#This Row],[ACTIVIDAD]],'Lista Maestra'!$D$6:$F$190,2,0),"") -> 0 | L69: CON ACTIVIDAD | N69: 0.40625 | O69: 0.44375 | P69: =IF(MUESTREO_LABORAL_A2[[#This Row],[TIEMPO INICIO]]="","",(MUESTREO_LABORAL_A2[[#This Row],[TIEMPO FIN]]-MUESTREO_LABORAL_A2[[#This Row],[TIEMPO INICIO]])*24) -> 0.9 | Q69: voy avanzar con programacion de platano, piñas y cacao lo de banano casi culminado hasta que confirme operaciones si algo mas van a programar. culmine lo que es la recopilacion de las solicitudes de mañana
B70: SMART | C70: PLANIFICACIÓN | D70: PLANIFICADOR | E70: BRANCO DÁVILA | F70: 45980 | I70: PROGRAMACIÓN DE TRANSPORTE | J70: =IFERROR(VLOOKUP(MUESTREO_LABORAL_A2[[#This Row],[ACTIVIDAD]],'Lista Maestra'!$D$6:$F$190,3,0),"") -> RECEPCIÓN DE SOLICITUD DE TRANSPORTE | K70: =IFERROR(VLOOKUP(MUESTREO_LABORAL_A2[[#This Row],[ACTIVIDAD]],'Lista Maestra'!$D$6:$F$190,2,0),"") -> CUADRE DE VEHÍCULOS EN BASE A LOS CORTES QUE ESTÁN PROGRAMADOS. REVISIÓN SOLICITUD DE OMARSA REVISIÓN LISTADO DE PROVEEDORES DE TRANSPORTE. REVISIÓN ASIGNACIÓN DE CHOFERES TANTO PROVEEDORES DE TRANSPORTE COMO PROVEEDORES PROPIOS. GENERACIÓN DE PLANIFICACIÓN DE TRANSPORTE DEL CORTE DEL MARTES. PLANIFICACIÓN DE BANANO REVISA EN FTL Y SE LO UBICA EN LA BASE DE TRANSPORTE. | L70: CON ACTIVIDAD | N70: 0.44375 | O70: 0.5125 | P70: =IF(MUESTREO_LABORAL_A2[[#This Row],[TIEMPO INICIO]]="","",(MUESTREO_LABORAL_A2[[#This Row],[TIEMPO FIN]]-MUESTREO_LABORAL_A2[[#This Row],[TIEMPO INICIO]])*24) -> 1.65 | Q70: ahora a gestionar planificacion de vehiculos vs la cantidad de procesos para mañana Dentro del proceso de revisar cantidades tambien reviso los vehiculos terceros fijos que viajan en el dia presente puertos en los que entregan si salen sellado o no para en base a esos indicadores tener de posible hora en que estaria desocupado y si avanza a viajar al dia siguiente ya definido lo antes mencionado y asignado los vehiculos de smart indentifico que cantidad me falta de vehiculos cubrir ahora debo revisar proveedores que no esten viajando de preferencia en que horarios estan desocupados los carros.
B71: SMART | C71: PLANIFICACIÓN | D71: PLANIFICADOR | E71: BRANCO DÁVILA | F71: 45980 | I71: NECESIDADES BIOLÓGICAS | J71: =IFERROR(VLOOKUP(MUESTREO_LABORAL_A2[[#This Row],[ACTIVIDAD]],'Lista Maestra'!$D$6:$F$190,3,0),"") -> NECESIDADES BIOLÓGICAS | K71: =IFERROR(VLOOKUP(MUESTREO_LABORAL_A2[[#This Row],[ACTIVIDAD]],'Lista Maestra'!$D$6:$F$190,2,0),"") -> PROCESO DE MICCIÓN Y AGREGADOS | N71: 0.5125 | O71: 0.52291667 | P71: =IF(MUESTREO_LABORAL_A2[[#This Row],[TIEMPO INICIO]]="","",(MUESTREO_LABORAL_A2[[#This Row],[TIEMPO FIN]]-MUESTREO_LABORAL_A2[[#This Row],[TIEMPO INICIO]])*24) -> 0.25
B72: SMART | C72: PLANIFICACIÓN | D72: PLANIFICADOR | E72: BRANCO DÁVILA | F72: 45980 | I72: ALIMENTACIÓN | J72: =IFERROR(VLOOKUP(MUESTREO_LABORAL_A2[[#This Row],[ACTIVIDAD]],'Lista Maestra'!$D$6:$F$190,3,0),"") -> ALIMENTACIÓN | K72: =IFERROR(VLOOKUP(MUESTREO_LABORAL_A2[[#This Row],[ACTIVIDAD]],'Lista Maestra'!$D$6:$F$190,2,0),"") -> ALIMENTARSE | N72: 0.52291667 | O72: 0.55694444 | P72: =IF(MUESTREO_LABORAL_A2[[#This Row],[TIEMPO INICIO]]="","",(MUESTREO_LABORAL_A2[[#This Row],[TIEMPO FIN]]-MUESTREO_LABORAL_A2[[#This Row],[TIEMPO INICIO]])*24) -> 0.81666667
B73: SMART | C73: PLANIFICACIÓN | D73: PLANIFICADOR | E73: BRANCO DÁVILA | F73: 45980 | I73: PROGRAMACIÓN DE TRANSPORTE | J73: =IFERROR(VLOOKUP(MUESTREO_LABORAL_A2[[#This Row],[ACTIVIDAD]],'Lista Maestra'!$D$6:$F$190,3,0),"") -> RECEPCIÓN DE SOLICITUD DE TRANSPORTE | K73: =IFERROR(VLOOKUP(MUESTREO_LABORAL_A2[[#This Row],[ACTIVIDAD]],'Lista Maestra'!$D$6:$F$190,2,0),"") -> CUADRE DE VEHÍCULOS EN BASE A LOS CORTES QUE ESTÁN PROGRAMADOS. REVISIÓN SOLICITUD DE OMARSA REVISIÓN LISTADO DE PROVEEDORES DE TRANSPORTE. REVISIÓN ASIGNACIÓN DE CHOFERES TANTO PROVEEDORES DE TRANSPORTE COMO PROVEEDORES PROPIOS. GENERACIÓN DE PLANIFICACIÓN DE TRANSPORTE DEL CORTE DEL MARTES. PLANIFICACIÓN DE BANANO REVISA EN FTL Y SE LO UBICA EN LA BASE DE TRANSPORTE. | L73: CON ACTIVIDAD | N73: 0.55694444 | O73: 0.57777778 | P73: =IF(MUESTREO_LABORAL_A2[[#This Row],[TIEMPO INICIO]]="","",(MUESTREO_LABORAL_A2[[#This Row],[TIEMPO FIN]]-MUESTREO_LABORAL_A2[[#This Row],[TIEMPO INICIO]])*24) -> 0.5 | Q73: Lo que es planifiacion de transporte, hasta el momento ya finalizado. Voy avanzar con los horometros de los viajes con generador que no esta culminado.
B74: SMART | C74: PLANIFICACIÓN | D74: PLANIFICADOR | E74: BRANCO DÁVILA | F74: 45980 | I74: HORÓMETROS DE VIAJE CON GENERADOR | J74: =IFERROR(VLOOKUP(MUESTREO_LABORAL_A2[[#This Row],[ACTIVIDAD]],'Lista Maestra'!$D$6:$F$190,3,0),"") -> CONTROL DEL CUMPLIMIENTO DE LA CADENA DE FRÍO | K74: =IFERROR(VLOOKUP(MUESTREO_LABORAL_A2[[#This Row],[ACTIVIDAD]],'Lista Maestra'!$D$6:$F$190,2,0),"") -> 0 | L74: CON ACTIVIDAD | N74: 0.57777778 | O74: 0.64236111 | P74: =IF(MUESTREO_LABORAL_A2[[#This Row],[TIEMPO INICIO]]="","",(MUESTREO_LABORAL_A2[[#This Row],[TIEMPO FIN]]-MUESTREO_LABORAL_A2[[#This Row],[TIEMPO INICIO]])*24) -> 1.55 | Q74: basicamente lo que hago es revisar en el grupo de generadores de los propios y proveedores que hicieron viajes con generador, para piñas, platano y pescado y recopilar el respaldo visual ( video) para tener constancia de que salio desde la base a su destino y desde el destino al puerto respetando la cadena de frio. con los horometros por diferencia voy a constatar que se cumplan con las horas de encendido del generador y ctr
B75: SMART | C75: PLANIFICACIÓN | D75: PLANIFICADOR | E75: BRANCO DÁVILA | F75: 45980 | I75: PROGRAMACIÓN DE TRANSPORTE | J75: =IFERROR(VLOOKUP(MUESTREO_LABORAL_A2[[#This Row],[ACTIVIDAD]],'Lista Maestra'!$D$6:$F$190,3,0),"") -> RECEPCIÓN DE SOLICITUD DE TRANSPORTE | K75: =IFERROR(VLOOKUP(MUESTREO_LABORAL_A2[[#This Row],[ACTIVIDAD]],'Lista Maestra'!$D$6:$F$190,2,0),"") -> CUADRE DE VEHÍCULOS EN BASE A LOS CORTES QUE ESTÁN PROGRAMADOS. REVISIÓN SOLICITUD DE OMARSA REVISIÓN LISTADO DE PROVEEDORES DE TRANSPORTE. REVISIÓN ASIGNACIÓN DE CHOFERES TANTO PROVEEDORES DE TRANSPORTE COMO PROVEEDORES PROPIOS. GENERACIÓN DE PLANIFICACIÓN DE TRANSPORTE DEL CORTE DEL MARTES. PLANIFICACIÓN DE BANANO REVISA EN FTL Y SE LO UBICA EN LA BASE DE TRANSPORTE. | L75: CON ACTIVIDAD | N75: 0.64236111 | O75: 0.70833333 | P75: =IF(MUESTREO_LABORAL_A2[[#This Row],[TIEMPO INICIO]]="","",(MUESTREO_LABORAL_A2[[#This Row],[TIEMPO FIN]]-MUESTREO_LABORAL_A2[[#This Row],[TIEMPO INICIO]])*24) -> 1.5833333
B76: SMART | C76: PLANIFICACIÓN | D76: PLANIFICADOR | E76: BRANCO DÁVILA | F76: 45981 | I76: AJUSTE DE PROGRAMACIÓN DE DESPACHO | J76: =IFERROR(VLOOKUP(MUESTREO_LABORAL_A2[[#This Row],[ACTIVIDAD]],'Lista Maestra'!$D$6:$F$190,3,0),"") -> PLANIFICACIÓN | K76: =IFERROR(VLOOKUP(MUESTREO_LABORAL_A2[[#This Row],[ACTIVIDAD]],'Lista Maestra'!$D$6:$F$190,2,0),"") -> CON RESPECTO AL DÍA ANTERIOR. | L76: CON ACTIVIDAD | N76: 0.35416667 | O76: 0.38541667 | P76: =IF(MUESTREO_LABORAL_A2[[#This Row],[TIEMPO INICIO]]="","",(MUESTREO_LABORAL_A2[[#This Row],[TIEMPO FIN]]-MUESTREO_LABORAL_A2[[#This Row],[TIEMPO INICIO]])*24) -> 0.75 | Q76: que ajustes se pueden hacer estamos atrasados en los posicionamientos por temas de congestion de retiros en los depositos
B77: SMART | C77: PLANIFICACIÓN | D77: PLANIFICADOR | E77: BRANCO DÁVILA | F77: 45981 | I77: PROGRAMACIÓN DE TRANSPORTE | J77: =IFERROR(VLOOKUP(MUESTREO_LABORAL_A2[[#This Row],[ACTIVIDAD]],'Lista Maestra'!$D$6:$F$190,3,0),"") -> RECEPCIÓN DE SOLICITUD DE TRANSPORTE | K77: =IFERROR(VLOOKUP(MUESTREO_LABORAL_A2[[#This Row],[ACTIVIDAD]],'Lista Maestra'!$D$6:$F$190,2,0),"") -> CUADRE DE VEHÍCULOS EN BASE A LOS CORTES QUE ESTÁN PROGRAMADOS. REVISIÓN SOLICITUD DE OMARSA REVISIÓN LISTADO DE PROVEEDORES DE TRANSPORTE. REVISIÓN ASIGNACIÓN DE CHOFERES TANTO PROVEEDORES DE TRANSPORTE COMO PROVEEDORES PROPIOS. GENERACIÓN DE PLANIFICACIÓN DE TRANSPORTE DEL CORTE DEL MARTES. PLANIFICACIÓN DE BANANO REVISA EN FTL Y SE LO UBICA EN LA BASE DE TRANSPORTE. | L77: CON ACTIVIDAD | N77: 0.38541667 | O77: 0.43611111 | P77: =IF(MUESTREO_LABORAL_A2[[#This Row],[TIEMPO INICIO]]="","",(MUESTREO_LABORAL_A2[[#This Row],[TIEMPO FIN]]-MUESTREO_LABORAL_A2[[#This Row],[TIEMPO INICIO]])*24) -> 1.2166667
B78: SMART | C78: PLANIFICACIÓN | D78: PLANIFICADOR | E78: BRANCO DÁVILA | F78: 45981 | I78: REVISIÓN VEHÍCULOS LOGÍSTICA | J78: =IFERROR(VLOOKUP(MUESTREO_LABORAL_A2[[#This Row],[ACTIVIDAD]],'Lista Maestra'!$D$6:$F$190,3,0),"") -> GESTIÓN DE LA PLANIFICACIÓN | K78: =IFERROR(VLOOKUP(MUESTREO_LABORAL_A2[[#This Row],[ACTIVIDAD]],'Lista Maestra'!$D$6:$F$190,2,0),"") -> 0 | L78: CON ACTIVIDAD | N78: 0.43611111 | O78: 0.44166667 | P78: =IF(MUESTREO_LABORAL_A2[[#This Row],[TIEMPO INICIO]]="","",(MUESTREO_LABORAL_A2[[#This Row],[TIEMPO FIN]]-MUESTREO_LABORAL_A2[[#This Row],[TIEMPO INICIO]])*24) -> 0.13333333 | Q78: revisando los vehiculos que estan en proceso de retiro y posionamiento en finca revisando con Ricardo que hay retrasos con las salidas a finca
B79: SMART | C79: PLANIFICACIÓN | D79: PLANIFICADOR | E79: BRANCO DÁVILA | F79: 45981 | I79: PROGRAMACIÓN DE TRANSPORTE | J79: =IFERROR(VLOOKUP(MUESTREO_LABORAL_A2[[#This Row],[ACTIVIDAD]],'Lista Maestra'!$D$6:$F$190,3,0),"") -> RECEPCIÓN DE SOLICITUD DE TRANSPORTE | K79: =IFERROR(VLOOKUP(MUESTREO_LABORAL_A2[[#This Row],[ACTIVIDAD]],'Lista Maestra'!$D$6:$F$190,2,0),"") -> CUADRE DE VEHÍCULOS EN BASE A LOS CORTES QUE ESTÁN PROGRAMADOS. REVISIÓN SOLICITUD DE OMARSA REVISIÓN LISTADO DE PROVEEDORES DE TRANSPORTE. REVISIÓN ASIGNACIÓN DE CHOFERES TANTO PROVEEDORES DE TRANSPORTE COMO PROVEEDORES PROPIOS. GENERACIÓN DE PLANIFICACIÓN DE TRANSPORTE DEL CORTE DEL MARTES. PLANIFICACIÓN DE BANANO REVISA EN FTL Y SE LO UBICA EN LA BASE DE TRANSPORTE. | L79: CON ACTIVIDAD | N79: 0.44166667 | O79: 0.52083333 | P79: =IF(MUESTREO_LABORAL_A2[[#This Row],[TIEMPO INICIO]]="","",(MUESTREO_LABORAL_A2[[#This Row],[TIEMPO FIN]]-MUESTREO_LABORAL_A2[[#This Row],[TIEMPO INICIO]])*24) -> 1.9
B80: SMART | C80: PLANIFICACIÓN | D80: PLANIFICADOR | E80: BRANCO DÁVILA | F80: 45981 | I80: NECESIDADES BIOLÓGICAS | J80: =IFERROR(VLOOKUP(MUESTREO_LABORAL_A2[[#This Row],[ACTIVIDAD]],'Lista Maestra'!$D$6:$F$190,3,0),"") -> NECESIDADES BIOLÓGICAS | K80: =IFERROR(VLOOKUP(MUESTREO_LABORAL_A2[[#This Row],[ACTIVIDAD]],'Lista Maestra'!$D$6:$F$190,2,0),"") -> PROCESO DE MICCIÓN Y AGREGADOS | N80: 0.52083333 | O80: 0.53125 | P80: =IF(MUESTREO_LABORAL_A2[[#This Row],[TIEMPO INICIO]]="","",(MUESTREO_LABORAL_A2[[#This Row],[TIEMPO FIN]]-MUESTREO_LABORAL_A2[[#This Row],[TIEMPO INICIO]])*24) -> 0.25
B81: SMART | C81: PLANIFICACIÓN | D81: PLANIFICADOR | E81: BRANCO DÁVILA | F81: 45981 | I81: ALIMENTACIÓN | J81: =IFERROR(VLOOKUP(MUESTREO_LABORAL_A2[[#This Row],[ACTIVIDAD]],'Lista Maestra'!$D$6:$F$190,3,0),"") -> ALIMENTACIÓN | K81: =IFERROR(VLOOKUP(MUESTREO_LABORAL_A2[[#This Row],[ACTIVIDAD]],'Lista Maestra'!$D$6:$F$190,2,0),"") -> ALIMENTARSE | N81: 0.53125 | O81: 0.55208333 | P81: =IF(MUESTREO_LABORAL_A2[[#This Row],[TIEMPO INICIO]]="","",(MUESTREO_LABORAL_A2[[#This Row],[TIEMPO FIN]]-MUESTREO_LABORAL_A2[[#This Row],[TIEMPO INICIO]])*24) -> 0.5
B82: SMART | C82: PLANIFICACIÓN | D82: PLANIFICADOR | E82: BRANCO DÁVILA | F82: 45981 | I82: REVISIÓN DE FACTURAS DE GENERADORES | J82: =IFERROR(VLOOKUP(MUESTREO_LABORAL_A2[[#This Row],[ACTIVIDAD]],'Lista Maestra'!$D$6:$F$190,3,0),"") -> CONTROL DOCUMENTAL DE PROVEDURÍA | K82: =IFERROR(VLOOKUP(MUESTREO_LABORAL_A2[[#This Row],[ACTIVIDAD]],'Lista Maestra'!$D$6:$F$190,2,0),"") -> 0 | L82: CON ACTIVIDAD | N82: 0.55208333 | O82: 0.5625 | P82: =IF(MUESTREO_LABORAL_A2[[#This Row],[TIEMPO INICIO]]="","",(MUESTREO_LABORAL_A2[[#This Row],[TIEMPO FIN]]-MUESTREO_LABORAL_A2[[#This Row],[TIEMPO INICIO]])*24) -> 0.25 | Q82: voy a revisar unas facturas de uso de generadores que alquilados si todo corresponde a los usos. Descartar actividad, aun no me pasan las fac
B83: SMART | C83: PLANIFICACIÓN | D83: PLANIFICADOR | E83: BRANCO DÁVILA | F83: 45981 | I83: HORÓMETROS DE VIAJE CON GENERADOR | J83: =IFERROR(VLOOKUP(MUESTREO_LABORAL_A2[[#This Row],[ACTIVIDAD]],'Lista Maestra'!$D$6:$F$190,3,0),"") -> CONTROL DEL CUMPLIMIENTO DE LA CADENA DE FRÍO | K83: =IFERROR(VLOOKUP(MUESTREO_LABORAL_A2[[#This Row],[ACTIVIDAD]],'Lista Maestra'!$D$6:$F$190,2,0),"") -> 0 | L83: CON ACTIVIDAD | N83: 0.5625 | O83: 0.70833333 | P83: =IF(MUESTREO_LABORAL_A2[[#This Row],[TIEMPO INICIO]]="","",(MUESTREO_LABORAL_A2[[#This Row],[TIEMPO FIN]]-MUESTREO_LABORAL_A2[[#This Row],[TIEMPO INICIO]])*24) -> 3.5
B84: TSER | C84: CONTABILIDAD | D84: ANALISTA CONTABLE | E84: MELANIE MIRANDA | F84: 45985 | I84: DEFINICIÓN | J84: =IFERROR(VLOOKUP(MUESTREO_LABORAL_A2[[#This Row],[ACTIVIDAD]],'Lista Maestra'!$D$6:$F$190,3,0),"") -> DEFINICIÓN | K84: =IFERROR(VLOOKUP(MUESTREO_LABORAL_A2[[#This Row],[ACTIVIDAD]],'Lista Maestra'!$D$6:$F$190,2,0),"") -> DEFINIR PROCESOS Y CRITERIOS INGENIERILES | L84: DEFINICIÓN | N84: 0.35416667 | O84: 0.38333333 | P84: =IF(MUESTREO_LABORAL_A2[[#This Row],[TIEMPO INICIO]]="","",(MUESTREO_LABORAL_A2[[#This Row],[TIEMPO FIN]]-MUESTREO_LABORAL_A2[[#This Row],[TIEMPO INICIO]])*24) -> 0.7
B85: TSER | C85: CONTABILIDAD | D85: ANALISTA CONTABLE | E85: MELANIE MIRANDA | F85: 45985 | I85: Creación de proveedores y artículos en Sap | J85: =IFERROR(VLOOKUP(MUESTREO_LABORAL_A2[[#This Row],[ACTIVIDAD]],'Lista Maestra'!$D$6:$F$190,3,0),"") -> CREACIÓN SAP | K85: =IFERROR(VLOOKUP(MUESTREO_LABORAL_A2[[#This Row],[ACTIVIDAD]],'Lista Maestra'!$D$6:$F$190,2,0),"") -> Realizar la creación de nuevos proveedores, creación de nuevos artículos solicitados por los departamentos establecidos. | L85: CON ACTIVIDAD | N85: 0.38333333 | O85: 0.38680556 | P85: =IF(MUESTREO_LABORAL_A2[[#This Row],[TIEMPO INICIO]]="","",(MUESTREO_LABORAL_A2[[#This Row],[TIEMPO FIN]]-MUESTREO_LABORAL_A2[[#This Row],[TIEMPO INICIO]])*24) -> 0.083333333
B86: TSER | C86: CONTABILIDAD | D86: ANALISTA CONTABLE | E86: MELANIE MIRANDA | F86: 45985 | I86: Revisar y analizar cobros de contenedores | J86: =IFERROR(VLOOKUP(MUESTREO_LABORAL_A2[[#This Row],[ACTIVIDAD]],'Lista Maestra'!$D$6:$F$190,3,0),"") -> GESTIÓN DOCUMENTAL | K86: =IFERROR(VLOOKUP(MUESTREO_LABORAL_A2[[#This Row],[ACTIVIDAD]],'Lista Maestra'!$D$6:$F$190,2,0),"") -> Análisis y revisión del reporte de cobro de contenedores (Andrea Bowen) a productores directos y por medio de liquidación BANANO-aplicación de criterios | L86: CON ACTIVIDAD | N86: 0.38680556 | O86: 0.4375 | P86: =IF(MUESTREO_LABORAL_A2[[#This Row],[TIEMPO INICIO]]="","",(MUESTREO_LABORAL_A2[[#This Row],[TIEMPO FIN]]-MUESTREO_LABORAL_A2[[#This Row],[TIEMPO INICIO]])*24) -> 1.2166667 | Q86: ya terminé de hablar con Oscar, ahora voy a indicar a las chicas sobre el caso de las 165 cajas que quedaron pendiente
B87: TSER | C87: CONTABILIDAD | D87: ANALISTA CONTABLE | E87: MELANIE MIRANDA | F87: 45985 | I87: Control y seguimiento de soportes y escaneos documentales | J87: =IFERROR(VLOOKUP(MUESTREO_LABORAL_A2[[#This Row],[ACTIVIDAD]],'Lista Maestra'!$D$6:$F$190,3,0),"") -> GESTIÓN DOCUMENTAL | K87: =IFERROR(VLOOKUP(MUESTREO_LABORAL_A2[[#This Row],[ACTIVIDAD]],'Lista Maestra'!$D$6:$F$190,2,0),"") -> Realizar el control y seguimiento de los soportes físicos y escaneados de los viajes, en coordinación con los responsables de garita, para el envío al cliente OLAM. la validación documental final es efectuada por melanie villa. | L87: CON ACTIVIDAD | N87: 0.38819444 | O87: 0.38958333 | P87: =IF(MUESTREO_LABORAL_A2[[#This Row],[TIEMPO INICIO]]="","",(MUESTREO_LABORAL_A2[[#This Row],[TIEMPO FIN]]-MUESTREO_LABORAL_A2[[#This Row],[TIEMPO INICIO]])*24) -> 0.033333333
B88: TSER | C88: CONTABILIDAD | D88: ANALISTA CONTABLE | E88: MELANIE MIRANDA | F88: 45985 | I88: Consolidado de transporte | J88: =IFERROR(VLOOKUP(MUESTREO_LABORAL_A2[[#This Row],[ACTIVIDAD]],'Lista Maestra'!$D$6:$F$190,3,0),"") -> PLANIFICACIÓN | K88: =IFERROR(VLOOKUP(MUESTREO_LABORAL_A2[[#This Row],[ACTIVIDAD]],'Lista Maestra'!$D$6:$F$190,2,0),"") -> Elaborar y actualizar el consolidado semanal de viajes, integrando la información de los diferentes reportes de transporte. | L88: CON ACTIVIDAD | N88: 0.38958333 | O88: 0.39375 | P88: =IF(MUESTREO_LABORAL_A2[[#This Row],[TIEMPO INICIO]]="","",(MUESTREO_LABORAL_A2[[#This Row],[TIEMPO FIN]]-MUESTREO_LABORAL_A2[[#This Row],[TIEMPO INICIO]])*24) -> 0.1
B89: TSER | C89: CONTABILIDAD | D89: ANALISTA CONTABLE | E89: MELANIE MIRANDA | F89: 45985 | I89: Control y seguimiento de soportes y escaneos documentales | J89: =IFERROR(VLOOKUP(MUESTREO_LABORAL_A2[[#This Row],[ACTIVIDAD]],'Lista Maestra'!$D$6:$F$190,3,0),"") -> GESTIÓN DOCUMENTAL | K89: =IFERROR(VLOOKUP(MUESTREO_LABORAL_A2[[#This Row],[ACTIVIDAD]],'Lista Maestra'!$D$6:$F$190,2,0),"") -> Realizar el control y seguimiento de los soportes físicos y escaneados de los viajes, en coordinación con los responsables de garita, para el envío al cliente OLAM. la validación documental final es efectuada por melanie villa. | L89: CON ACTIVIDAD | N89: 0.39375 | O89: 0.39722222 | P89: =IF(MUESTREO_LABORAL_A2[[#This Row],[TIEMPO INICIO]]="","",(MUESTREO_LABORAL_A2[[#This Row],[TIEMPO FIN]]-MUESTREO_LABORAL_A2[[#This Row],[TIEMPO INICIO]])*24) -> 0.083333333
B90: TSER | C90: CONTABILIDAD | D90: ANALISTA CONTABLE | E90: MELANIE MIRANDA | F90: 45985 | I90: Consolidado de transporte | J90: =IFERROR(VLOOKUP(MUESTREO_LABORAL_A2[[#This Row],[ACTIVIDAD]],'Lista Maestra'!$D$6:$F$190,3,0),"") -> PLANIFICACIÓN | K90: =IFERROR(VLOOKUP(MUESTREO_LABORAL_A2[[#This Row],[ACTIVIDAD]],'Lista Maestra'!$D$6:$F$190,2,0),"") -> Elaborar y actualizar el consolidado semanal de viajes, integrando la información de los diferentes reportes de transporte. | L90: CON ACTIVIDAD | N90: 0.39722222 | O90: 0.40069444 | P90: =IF(MUESTREO_LABORAL_A2[[#This Row],[TIEMPO INICIO]]="","",(MUESTREO_LABORAL_A2[[#This Row],[TIEMPO FIN]]-MUESTREO_LABORAL_A2[[#This Row],[TIEMPO INICIO]])*24) -> 0.083333333
B91: TSER | C91: CONTABILIDAD | D91: ANALISTA CONTABLE | E91: MELANIE MIRANDA | F91: 45985 | I91: Control y seguimiento de soportes y escaneos documentales | J91: =IFERROR(VLOOKUP(MUESTREO_LABORAL_A2[[#This Row],[ACTIVIDAD]],'Lista Maestra'!$D$6:$F$190,3,0),"") -> GESTIÓN DOCUMENTAL | K91: =IFERROR(VLOOKUP(MUESTREO_LABORAL_A2[[#This Row],[ACTIVIDAD]],'Lista Maestra'!$D$6:$F$190,2,0),"") -> Realizar el control y seguimiento de los soportes físicos y escaneados de los viajes, en coordinación con los responsables de garita, para el envío al cliente OLAM. la validación documental final es efectuada por melanie villa. | L91: CON ACTIVIDAD | N91: 0.39722222 | O91: 0.4375 | P91: =IF(MUESTREO_LABORAL_A2[[#This Row],[TIEMPO INICIO]]="","",(MUESTREO_LABORAL_A2[[#This Row],[TIEMPO FIN]]-MUESTREO_LABORAL_A2[[#This Row],[TIEMPO INICIO]])*24) -> 0.96666667 | Q91: haré la act 24, que es llamar al cliente para indicarle que se anuló con nc las fact y no se podrá facturar, por lo que le comenté ya que ella estaba esperando para el día de hoy que le facture
B92: TSER | C92: CONTABILIDAD | D92: ANALISTA CONTABLE | E92: MELANIE MIRANDA | F92: 45985 | I92: Control y validación de reporte de transporte de contenedor | J92: =IFERROR(VLOOKUP(MUESTREO_LABORAL_A2[[#This Row],[ACTIVIDAD]],'Lista Maestra'!$D$6:$F$190,3,0),"") -> PLANIFICACIÓN | K92: =IFERROR(VLOOKUP(MUESTREO_LABORAL_A2[[#This Row],[ACTIVIDAD]],'Lista Maestra'!$D$6:$F$190,2,0),"") -> Realizar la verificación y validación del reporte de viajes elaborado por el responsable del área (Oscar Ortega), asegurando que las tarifas se encuentren correctamente actualizadas conforme a lo establecido en el tarifario. Además, detallar los códigos de artículos correspondientes para el control y registro de las facturas emitidas por cada transportista. Asignar los activos | L92: CON ACTIVIDAD | N92: 0.39861111 | O92: 0.42986111 | P92: =IF(MUESTREO_LABORAL_A2[[#This Row],[TIEMPO INICIO]]="","",(MUESTREO_LABORAL_A2[[#This Row],[TIEMPO FIN]]-MUESTREO_LABORAL_A2[[#This Row],[TIEMPO INICIO]])*24) -> 0.75
B93: TSER | C93: CONTABILIDAD | D93: ANALISTA CONTABLE | E93: MELANIE MIRANDA | F93: 45985 | I93: Elaborar y revisar reportes de cobro de ingreso de contenedores | J93: =IFERROR(VLOOKUP(MUESTREO_LABORAL_A2[[#This Row],[ACTIVIDAD]],'Lista Maestra'!$D$6:$F$190,3,0),"") -> GESTIÓN DOCUMENTAL | K93: =IFERROR(VLOOKUP(MUESTREO_LABORAL_A2[[#This Row],[ACTIVIDAD]],'Lista Maestra'!$D$6:$F$190,2,0),"") -> Elaboración de plantillas y guias en SAP de retiros de contenedores, se enviá la factura mediante correo adjuntando el soporte (statement) y en SAP se procede a reclasificar por semanas | L93: CON ACTIVIDAD | N93: 0.4375 | O93: 0.44097222 | P93: =IF(MUESTREO_LABORAL_A2[[#This Row],[TIEMPO INICIO]]="","",(MUESTREO_LABORAL_A2[[#This Row],[TIEMPO FIN]]-MUESTREO_LABORAL_A2[[#This Row],[TIEMPO INICIO]])*24) -> 0.083333333 | Q93: haré la actividad 28 nomas, ya que queria facturar otros temas, pero no abre sap lo que haré es un envío de las fact y un archivo al cliente, ya que ya lo facturé la sem pasada
B94: TSER | C94: CONTABILIDAD | D94: ANALISTA CONTABLE | E94: MELANIE MIRANDA | F94: 45985 | I94: Control y validación de reporte de transporte de contenedor | J94: =IFERROR(VLOOKUP(MUESTREO_LABORAL_A2[[#This Row],[ACTIVIDAD]],'Lista Maestra'!$D$6:$F$190,3,0),"") -> PLANIFICACIÓN | K94: =IFERROR(VLOOKUP(MUESTREO_LABORAL_A2[[#This Row],[ACTIVIDAD]],'Lista Maestra'!$D$6:$F$190,2,0),"") -> Realizar la verificación y validación del reporte de viajes elaborado por el responsable del área (Oscar Ortega), asegurando que las tarifas se encuentren correctamente actualizadas conforme a lo establecido en el tarifario. Además, detallar los códigos de artículos correspondientes para el control y registro de las facturas emitidas por cada transportista. Asignar los activos | L94: CON ACTIVIDAD | N94: 0.44097222 | O94: 0.44583333 | P94: =IF(MUESTREO_LABORAL_A2[[#This Row],[TIEMPO INICIO]]="","",(MUESTREO_LABORAL_A2[[#This Row],[TIEMPO FIN]]-MUESTREO_LABORAL_A2[[#This Row],[TIEMPO INICIO]])*24) -> 0.11666667 | Q94: revisando un contenedor que me indican las chicas
B95: TSER | C95: CONTABILIDAD | D95: ANALISTA CONTABLE | E95: MELANIE MIRANDA | F95: 45985 | I95: Atención a consultas de productores sobre la facturación | J95: =IFERROR(VLOOKUP(MUESTREO_LABORAL_A2[[#This Row],[ACTIVIDAD]],'Lista Maestra'!$D$6:$F$190,3,0),"") -> FACTURACIÓN | K95: =IFERROR(VLOOKUP(MUESTREO_LABORAL_A2[[#This Row],[ACTIVIDAD]],'Lista Maestra'!$D$6:$F$190,2,0),"") -> Explicación personalizada de facturaciones a productores vía telefónica, email, whatsapp, entre otros medios | L95: CON ACTIVIDAD | N95: 0.44583333 | O95: 0.44791667 | P95: =IF(MUESTREO_LABORAL_A2[[#This Row],[TIEMPO INICIO]]="","",(MUESTREO_LABORAL_A2[[#This Row],[TIEMPO FIN]]-MUESTREO_LABORAL_A2[[#This Row],[TIEMPO INICIO]])*24) -> 0.05
B96: TSER | C96: CONTABILIDAD | D96: ANALISTA CONTABLE | E96: MELANIE MIRANDA | F96: 45985 | I96: Elaborar y revisar reportes de cobro de movimiento de fruta. | J96: =IFERROR(VLOOKUP(MUESTREO_LABORAL_A2[[#This Row],[ACTIVIDAD]],'Lista Maestra'!$D$6:$F$190,3,0),"") -> GESTIÓN DOCUMENTAL | K96: =IFERROR(VLOOKUP(MUESTREO_LABORAL_A2[[#This Row],[ACTIVIDAD]],'Lista Maestra'!$D$6:$F$190,2,0),"") -> Analisis y revision del reporte de movimiento de fruta y bajo cubierta junto con Ricardo Salinas para envio a (Andrea Bowen) y elaboración de guías de remisión, para proceder con la facturación | L96: CON ACTIVIDAD | N96: 0.44791667 | O96: 0.46180556 | P96: =IF(MUESTREO_LABORAL_A2[[#This Row],[TIEMPO INICIO]]="","",(MUESTREO_LABORAL_A2[[#This Row],[TIEMPO FIN]]-MUESTREO_LABORAL_A2[[#This Row],[TIEMPO INICIO]])*24) -> 0.33333333
B97: TSER | C97: CONTABILIDAD | D97: ANALISTA CONTABLE | E97: MELANIE MIRANDA | F97: 45985 | I97: Consolidado de transporte | J97: =IFERROR(VLOOKUP(MUESTREO_LABORAL_A2[[#This Row],[ACTIVIDAD]],'Lista Maestra'!$D$6:$F$190,3,0),"") -> PLANIFICACIÓN | K97: =IFERROR(VLOOKUP(MUESTREO_LABORAL_A2[[#This Row],[ACTIVIDAD]],'Lista Maestra'!$D$6:$F$190,2,0),"") -> Elaborar y actualizar el consolidado semanal de viajes, integrando la información de los diferentes reportes de transporte. | L97: CON ACTIVIDAD | N97: 0.45625 | O97: 0.46180556 | P97: =IF(MUESTREO_LABORAL_A2[[#This Row],[TIEMPO INICIO]]="","",(MUESTREO_LABORAL_A2[[#This Row],[TIEMPO FIN]]-MUESTREO_LABORAL_A2[[#This Row],[TIEMPO INICIO]])*24) -> 0.13333333
B98: TSER | C98: CONTABILIDAD | D98: ANALISTA CONTABLE | E98: MELANIE MIRANDA | F98: 45985 | I98: Revisar y analizar cobros de contenedores | J98: =IFERROR(VLOOKUP(MUESTREO_LABORAL_A2[[#This Row],[ACTIVIDAD]],'Lista Maestra'!$D$6:$F$190,3,0),"") -> GESTIÓN DOCUMENTAL | K98: =IFERROR(VLOOKUP(MUESTREO_LABORAL_A2[[#This Row],[ACTIVIDAD]],'Lista Maestra'!$D$6:$F$190,2,0),"") -> Análisis y revisión del reporte de cobro de contenedores (Andrea Bowen) a productores directos y por medio de liquidación BANANO-aplicación de criterios | L98: CON ACTIVIDAD | N98: 0.46180556 | O98: 0.52083333 | P98: =IF(MUESTREO_LABORAL_A2[[#This Row],[TIEMPO INICIO]]="","",(MUESTREO_LABORAL_A2[[#This Row],[TIEMPO FIN]]-MUESTREO_LABORAL_A2[[#This Row],[TIEMPO INICIO]])*24) -> 1.4166667
B99: TSER | C99: CONTABILIDAD | D99: ANALISTA CONTABLE | E99: MELANIE MIRANDA | F99: 45985 | I99: Elaborar y revisar reportes de cobro de movimiento de fruta. | J99: =IFERROR(VLOOKUP(MUESTREO_LABORAL_A2[[#This Row],[ACTIVIDAD]],'Lista Maestra'!$D$6:$F$190,3,0),"") -> GESTIÓN DOCUMENTAL | K99: =IFERROR(VLOOKUP(MUESTREO_LABORAL_A2[[#This Row],[ACTIVIDAD]],'Lista Maestra'!$D$6:$F$190,2,0),"") -> Analisis y revision del reporte de movimiento de fruta y bajo cubierta junto con Ricardo Salinas para envio a (Andrea Bowen) y elaboración de guías de remisión, para proceder con la facturación | L99: CON ACTIVIDAD | N99: 0.47638889 | O99: 0.52083333 | P99: =IF(MUESTREO_LABORAL_A2[[#This Row],[TIEMPO INICIO]]="","",(MUESTREO_LABORAL_A2[[#This Row],[TIEMPO FIN]]-MUESTREO_LABORAL_A2[[#This Row],[TIEMPO INICIO]])*24) -> 1.0666667
B100: TSER | C100: CONTABILIDAD | D100: ANALISTA CONTABLE | E100: MELANIE MIRANDA | F100: 45985 | I100: Control y validación de reporte de transporte de contenedor | J100: =IFERROR(VLOOKUP(MUESTREO_LABORAL_A2[[#This Row],[ACTIVIDAD]],'Lista Maestra'!$D$6:$F$190,3,0),"") -> PLANIFICACIÓN | K100: =IFERROR(VLOOKUP(MUESTREO_LABORAL_A2[[#This Row],[ACTIVIDAD]],'Lista Maestra'!$D$6:$F$190,2,0),"") -> Realizar la verificación y validación del reporte de viajes elaborado por el responsable del área (Oscar Ortega), asegurando que las tarifas se encuentren correctamente actualizadas conforme a lo establecido en el tarifario. Además, detallar los códigos de artículos correspondientes para el control y registro de las facturas emitidas por cada transportista. Asignar los activos | L100: CON ACTIVIDAD | N100: 0.47638889 | O100: 0.48263889 | P100: =IF(MUESTREO_LABORAL_A2[[#This Row],[TIEMPO INICIO]]="","",(MUESTREO_LABORAL_A2[[#This Row],[TIEMPO FIN]]-MUESTREO_LABORAL_A2[[#This Row],[TIEMPO INICIO]])*24) -> 0.15
B101: TSER | C101: CONTABILIDAD | D101: ANALISTA CONTABLE | E101: MELANIE MIRANDA | F101: 45985 | I101: Verificación de anulación de retenciones | J101: =IFERROR(VLOOKUP(MUESTREO_LABORAL_A2[[#This Row],[ACTIVIDAD]],'Lista Maestra'!$D$6:$F$190,3,0),"") -> RETENCIONES | K101: =IFERROR(VLOOKUP(MUESTREO_LABORAL_A2[[#This Row],[ACTIVIDAD]],'Lista Maestra'!$D$6:$F$190,2,0),"") -> Verificar la correcta anulación de las retenciones registradas en sap, posterior a la anulación en el sistema, se efectúe la solicitud correspondiente en el portal del sri, garantizando la coherencia entre ambas plataformas y la trazabilidad del proceso contable. | L101: CON ACTIVIDAD | N101: 0.48263889 | O101: 0.52083333 | P101: =IF(MUESTREO_LABORAL_A2[[#This Row],[TIEMPO INICIO]]="","",(MUESTREO_LABORAL_A2[[#This Row],[TIEMPO FIN]]-MUESTREO_LABORAL_A2[[#This Row],[TIEMPO INICIO]])*24) -> 0.91666667
B102: TSER | C102: CONTABILIDAD | D102: ANALISTA CONTABLE | E102: MELANIE MIRANDA | F102: 45985 | I102: Gestionar facturación, notas de crédito y refacturaciones semanales de contenedores. | J102: =IFERROR(VLOOKUP(MUESTREO_LABORAL_A2[[#This Row],[ACTIVIDAD]],'Lista Maestra'!$D$6:$F$190,3,0),"") -> GESTIÓN DOCUMENTAL | K102: =IFERROR(VLOOKUP(MUESTREO_LABORAL_A2[[#This Row],[ACTIVIDAD]],'Lista Maestra'!$D$6:$F$190,2,0),"") -> Elaboración de informe de facturacion de contenedores, emisión de notas de credito por roleos y costos TFE, refacturaciones semanales de contenedores de productores varios y MLC | L102: CON ACTIVIDAD | N102: 0.51319444 | O102: 0.52083333 | P102: =IF(MUESTREO_LABORAL_A2[[#This Row],[TIEMPO INICIO]]="","",(MUESTREO_LABORAL_A2[[#This Row],[TIEMPO FIN]]-MUESTREO_LABORAL_A2[[#This Row],[TIEMPO INICIO]])*24) -> 0.18333333
B103: TSER | C103: CONTABILIDAD | D103: ANALISTA CONTABLE | E103: MELANIE MIRANDA | F103: 45985 | I103: ALIMENTACIÓN | J103: =IFERROR(VLOOKUP(MUESTREO_LABORAL_A2[[#This Row],[ACTIVIDAD]],'Lista Maestra'!$D$6:$F$190,3,0),"") -> ALIMENTACIÓN | K103: =IFERROR(VLOOKUP(MUESTREO_LABORAL_A2[[#This Row],[ACTIVIDAD]],'Lista Maestra'!$D$6:$F$190,2,0),"") -> ALIMENTARSE | L103: ALIMENTACIÓN | N103: 0.52083333 | O103: 0.5625 | P103: =IF(MUESTREO_LABORAL_A2[[#This Row],[TIEMPO INICIO]]="","",(MUESTREO_LABORAL_A2[[#This Row],[TIEMPO FIN]]-MUESTREO_LABORAL_A2[[#This Row],[TIEMPO INICIO]])*24) -> 1
...

Sheet Hoja1
D5: REUNIONES | E5: PROVEEDORES | F5: ENTRADAS | G5: PROCESO | H5: SALIDAS | I5: CLIENTES
D6: REALIZADO | E6: DANNY | F6: CONSOLIDADDO FTL/CONTROL PLÁTANO/ANTICIPO DE PAGO A PRODUCTORES/MAQUILAJE Y PALETIZADO | G6: CONTROL PLÁTANO | H6: PAGOS A PRODUCTORES/DATOS PARA FACTURACIÓN/DATOS DE LIQUIDACIÓN/DECLARACIÓN DE PLANES DE EMBARQUE PARA COMEX/FACTURACIÓN (MARLYS [REGISTRO DE FACTURAS DE FRUTA]/HAIDEY [FACTURACIÓN DE VENTA Y FACTURACIÓN REEMBOLSOS]) | I6: COMEX/TESORERIA
D7: REALIZADO | E7: MARITZA | F7: VENTAS DE MATERIALES
E8: ANDREA | F8: RESULTADOS DE CUENTAS POR COBRAR
E9: CESAR VALLE | F9: PLANES DE EMBARQUE
E10: MELANIE MIRANDA | F10: DESCUENTO DE TRANSPORTE DE MATERIALES

Sheet Lista Maestra
C5: EMPRESA | D5: ACTIVIDAD | E5: ACCIONES | F5: PROCESO | G5: TIPO DE ANALISIS | H5: DESCRIPCIÓN
C6: TSER | D6: FACTURACIÓN CIF BANANO A CLIENTES EN MULTINATIONAL | E6: ELABORACIÓN SEMANAL DE FACTURAS DE BANANO PARA CLIENTES INTERNACIONALES EN MULTINATIONAL, TRABAJANDO CON LOS REPORTES DE TRÁMITES DE LA SEMANA, DETALLE DE CONSOLIDACIÓN EN FTL Y B/LS CON CIERRE SEMANAL CORRESPONDIENTE. | F6: FACTURACIÓN A CLIENTES | G6: AUTOMATIZACIÓN | H6: Cuando se pueden realizar proyectos de mejora para reducir tiempos en actividades.
C7: TSER | D7: FACTURACIÓN CIF PLÁTANO A CLIENTES EN MULTINATIONAL | E7: ELABORACIÓN SEMANAL DE FACTURAS DE PLATANO PARA CLIENTES INTERNACIONALES EN MULTINATIONAL, TRABAJANDO CON LOS REPORTES DE TRÁMITES DE LA SEMANA, DETALLE DE CONSOLIDACIÓN EN FTL Y B/LS CON CIERRE SEMANAL CORRESPONDIENTE. | F7: FACTURACIÓN A CLIENTES | G7: ENC | H7: Es una entrada no conforme cuando las salidas de un proceso abajo (otro departamento) no envía la información correcta o la envía incompleta, lo cual genera pérdidas de tiempos en las actividades. Se debe colocar en la columna DEPARTAMENTO ENC el Departamento que genera la entrada no conforme.
C8: TSER | D8: CONSOLIDACIÓN DE VENTAS CÍAS RELACIONADAS A MLC | E8: REALIZACIÓN Y ANÁLISIS DE CONCILIACIONES DE VENTAS ENTRE EXPORTADORAS RELACIONADAS PARA VERIFICAR QUE LOS REGISTROS DE VENTAS ESTÉN CUADRADOS, IDENTIFICANDO DIFERENCIAS Y REGISTRANDO AJUSTES CONTABLES NECESARIOS. | F8: CONCILIACIÓN DE VENTAS Y COMPRAS ENTRE RELACIONADAS | G8: SA | H8: Cuando el colaborador no cuenta con actividades en el horario laboral o realiza actividades que no corresponden al cargo.
C9: TSER | D9: EMISIÓN DE NOTAS DE CRÉDITOS CLIENTES EN MULTINATIONAL (BANANO Y PLÁTANO) | E9: ELABORACIÓN DE NOTAS DE CRÉDITO SEGÚN AJUSTES DE PRECIOS, RECLAMOS DE FRUTAS, DEVOLUCIONES, VERIFICACIÓN DE MONTOS Y CLIENTES, REGISTRO DE LOS ASIENTOS CORRESPONDIENTES EN SAP, Y ACTUALIZACIÓN DE CUENTAS POR COBRAR. | F9: NOTAS DE CRÉDITO CLIENTES | G9: FALLO IT | H9: Cuando el sistema no permite que el colaborador avance con sus actividades debido a que no puede utilizar su computadora personal.
C10: TSER | D10: FACTURACIÓN DDP BANANO COSTCO | E10: ELABORACIÓN SEMANAL DE FACTURAS DE BANANO PARA CLIENTES INTERNACIONALES EN MULTINATIONAL, TRABAJANDO CON LOS REPORTES DE TRÁMITES DE LA SEMANA, DETALLE DE CONSOLIDACIÓN EN FTL Y B/LS, FACTURACIÓN SE REALIZA 21 DÍAS DESPUES DEL ZARPE DE LA CARGA | F10: FACTURACIÓN A CLIENTES | G10: CAPACITACIÓN | H10: Cuando un colaborador carece de expertiz en el desarrollo de una actividad como el uso de una herramienta técnológica o de comunicación.
C11: TSER | D11: EMISIÓN CERTIFICADOS DE EXPORTACIÓN | E11: ELABORACIÓN DE CERTIFICADOS PARA PRODUCTORES SEGÚN LOS MESES SOLICITADOS, INCLUYENDO EL DETALLE DE DAE, NÚMERO DE FACTURA DE VENTA, CANTIDAD DE CAJAS EXPORTADAS, FECHA DE CIERRE DE LAS DAE, VALOR TOTAL EN USD Y FACTURA DE COMPRA DEL PROVEEDOR. | F11: EMISIÓN CERTIFICADOS | G11: CON ACTIVIDAD | H11: Cuando el colaborador se encuentre realizando actividades que corresponden al cargo sin ningun tipo de retraso alguno.
C12: TSER | D12: REVISIÓN, GESTIÓN Y CONTROL DEL FLUJO DE CUENTAS POR PAGAR (INVOICES-MLC) MULTINATIONAL | E12: REGISTRO Y ANÁLISIS DE FACTURAS DE PROVEEDORES DEL EXTERIOR EN EL SISTEMA CONTABLE, SEGÚN APROBACIÓN DEL EQUIPO COMERCIAL, INCLUYENDO FACTURAS DE INSPECCIONES ADICIONALES A CONTENEDORES EXPORTADOS, YA SEA DE FORMA SEMANAL O MENSUAL (PROVEEDORES COMO SEABOARD, J&K, LARAS TRUCKING, RENE VELASQUEZ, HPL APOLLO, ETC.), VERIFICACIÓN Y ANÁLISIS DE DATOS Y MONTOS. | F12: CONTROL CUENTAS POR PAGAR | G12: DEFINICIÓN | H12: Inducción del muestreo de funciones a realizar en el balance de cargas de trabajo.
C13: TSER | D13: ASIENTOS POR DESCUENTOS A EMPLEADOS MEDIANTE ROL | E13: REGISTRO Y ANÁLISIS DE ASIENTOS DE DIARIO O DE RECLASIFICACIÓN EN CUENTAS POR COBRAR DE EMPLEADOS POR DESCUENTOS INDICADOS POR EL ÁREA DE RRHH, VERIFICANDO LA CONSISTENCIA DE MONTOS, CLASIFICACIÓN CONTABLE CORRECTA | F13: DESCUENTOS DE NÓMINA | G13: ALIMENTACIÓN | H13: Servicios de alimentación
C14: TSER | D14: ANALISIS Y CONCILIACION DE CUENTAS CONTABLES MENSUALES | E14: REALIZAR EL ANÁLISIS DETALLADO DE LAS CUENTAS CONTABLES MENSUALES, COMPARANDO SALDOS Y MOVIMIENTOS PARA IDENTIFICAR DISCREPANCIAS. | F14: ANÁLISIS DE CUENTAS | G14: NECESIDADES BIOLÓGICAS
C15: TSER | D15: CONCILIACION DE COMPRAS, VENTAS, SALDOS EN CUENTAS POR COBRAR ENTRE COMPAÑÍAS RELACIONADAS | E15: REALIZAR LA CONCILIACIÓN DE COMPRAS, VENTAS Y SALDOS EN CUENTAS POR COBRAR ENTRE COMPAÑÍAS RELACIONADAS, VERIFICANDO LA COHERENCIA DE LOS REGISTROS CONTABLES, DETECTANDO DIFERENCIAS Y REGISTRANDO LOS AJUSTES NECESARIOS | F15: CONCILIACIÓN RELACIONADAS
C16: TSER | D16: ELABORACIÓN DE REPORTES FINANCIEROS | E16: ELABORAR REPORTERÍA FINANCIERA MENSUAL PARA ELABORACIÓN DE BALANCES. | F16: REPORTERÍA
C17: TSER | D17: COMPARATIVO VENTAS MLC Y DECLARACION COFACE | E17: REALIZAR REPORTE, ANALISIS, COMPARACIÓN Y REVISIÓN DE LA INFORMACIÓN RECIBIDA POR CORREO DEL ÁREA FINANCIERA, VERIFICANDO QUE LO DECLARADO A COFACE COINCIDA CON LAS VENTAS REGISTRADAS EN LA CONTABILIDAD POR CLIENTE EN MULTINATIONAL. | F17: ANÁLISIS DE VENTAS
C18: TSER | D18: SOPORTE MEDIANTE AUDITORÍA EXTERNAS E INTERNAS | E18: PROPORCIONAR SOPORTE EN AUDITORÍAS TRIBUTARIAS, DE CARBONO NEUTRO Y OTROS PROCESOS DE CONTROL FINANCIERO. | F18: SOPORTE AUDITORÍA
C19: TSER | D19: ASISTENCIA TÉCNICA EN LA DETERMINACION DE RETENCIONES TRIBUTARIAS | E19: BRINDAR ASISTENCIA TÉCNICA EN LA DETERMINACIÓN DE RETENCIONES TRIBUTARIAS A LOS PRVOEEDORES, INCLUYENDO CÁLCULO SEGÚN NORMATIVA VIGENTE. | F19: ASISTENCIA EN IMPUESTO TRIBUTARIO
C20: TSER | D20: GESTIÓN CONTABLE Y CLASIFICACIÓN DE CUENTAS FINANCIERAS | E20: SE REALIZA LA GESTIÓN CONTABLE Y CLASIFICACIÓN DE CUENTAS FINANCIERAS, MEDIANTE LA REVISIÓN, ANÁLISIS Y REGISTRO DE LOS MOVIMIENTOS CONTABLES EN EL SISTEMA. SE CLASIFICAN LAS TRANSACCIONES SEGÚN SU NATURALEZA (ACTIVOS, PASIVOS, INGRESOS Y GASTOS) | F20: ANÁLISIS DE CUENTAS
C21: TSER | D21: GESTIÓN DE REPOSICIÓN Y CONTROL DE CAJA CHICA EL CARMEN Y EL PAN | E21: SE EJECUTA LA GESTIÓN DE REPOSICIÓN Y CONTROL DE CAJA CHICA, MEDIANTE LA REVISIÓN DE COMPROBANTES DE GASTO, VALIDACIÓN DE SOPORTES Y REGISTRO CONTABLE DE LOS MOVIMIENTOS EFECTUADOS. SE VERIFICA QUE LOS GASTOS SE ENCUENTREN DENTRO DE LAS POLÍTICAS INTERNAS Y SE PREPARA LA SOLICITUD DE REPOSICIÓN CORRESPONDIENTE. | F21: CONTROL DE CAJA CHICA
C22: TSER | D22: APOYO EN DECLARACIONS, ATS Y ANEXOS | E22: SE BRINDA APOYO EN LA ELABORACIÓN DE DECLARACIONES TRIBUTARIAS, ATS Y ANEXOS, MEDIANTE REPORTERÍA Y REVISIÓN DE INFORMACIÓN CONTABLE, VALIDANDO LOS DATOS REGISTRADOS EN EL SISTEMA. | F22: SOPORTE SRI
C23: TSER | D23: SUPERVISIÓN DE CIERRE CONTABLE EN CUENTAS POR PAGAR MENSUAL Y ANUAL | E23: SE EJECUTA LA SUPERVISIÓN Y EJECUCIÓN DEL CIERRE CONTABLE MENSUAL Y ANUAL DE LAS CUENTAS POR PAGAR, REVISANDO LOS REGISTROS DE FACTURAS DE COMPRA, RETENCIONES Y FACTURAS DE VENTA, ASÍ COMO LAS RECLASIFICACIONES NECESARIAS PARA MANTENER CORRECTA CONTABILIZACION DE GASTOS. | F23: SUPERVISIÓN EN CIERRE
C24: TSER | D24: CREACIÓN Y ACTUALIZACIÓN DE ARTÍCULOS Y CUENTAS CONTABLES EN SAP | E24: SE REALIZA LA CREACIÓN Y ACTUALIZACIÓN DE ARTÍCULOS Y CUENTAS CONTABLES DE BIENES O SERVICIOS EN SAP, SEGÚN LOS REQUERIMIENTOS DE LAS DEMÁS ÁREAS. | F24: CREACIÓN DE ARTÍCULOS
C25: TSER | D25: REVISION Y ANALISIS DE CUENTAS INGRESOS, COSTOS Y GASTOS | E25: SE REVISA Y ANALIZA LA INFORMACIÓN DE LAS CUENTAS DE INGRESOS, COSTOS Y GASTOS, VERIFICANDO QUE LOS REGISTROS CONTABLES ESTÉN CORRECTOS Y RESPALDADOS CON SU DOCUMENTACIÓN. SE COMPARAN LOS VALORES ENTRE PERIODOS Y SE IDENTIFICAN DIFERENCIAS PARA REALIZAR LOS AJUSTES O RECLASIFICACIONES NECESARIAS. | F25: ANÁLISIS DE CUENTAS
C26: TSER | D26: CONTROL DE CUENTAS POR PAGAR Y REVISIÓN DE GASTOS OPERATIVOS EN EXPORTADORAS | E26: SE REVISA Y CONTROLA LA INFORMACIÓN DE LAS CUENTAS POR PAGAR DE LAS EXPORTADORAS, VERIFICANDO QUE LAS FACTURAS DE COMPRA Y GASTOS OPERATIVOS ESTÉN CORRECTAMENTE REGISTRADOS, APROBADOS Y RESPALDADOS. SE REALIZAN SEGUIMIENTOS A LOS PROVEEDORES Y SE CONFIRMA QUE LOS VALORES COINCIDAN CON LOS REGISTROS CONTABLES. | F26: SUPERVISIÓN EN CIERRE
... C34: TSER | D34: REUNIONES Y COMITÉS | E34: SE PARTICIPA EN REUNIONES Y COMITÉS, DISCUTIENDO ASUNTOS CONTABLES Y COORDINANDO ACCIONES CON OTROS DEPARTAMENTOS PARA DAR SEGUIMIENTO A PROCESOS, AJUSTES Y REPORTES CONTABLES. | F34: REUNIONES
C35: TSER | D35: LIQUIDACIÓN - GASTOS ARROZ | F35: LIQUIDACIÓN DE GASTOS
C36: TSER | D36: SOPORTE INGRESO DE FACTURAS DE COMPRAS | F36: SUPERVISIÓN EN CIERRE
C37: TSER | D37: NECESIDADES BIOLÓGICAS | E37: PROCESO DE MICCIÓN Y AGREGADOS | F37: NECESIDADES BIOLÓGICAS
C38: TSER | D38: ALIMENTACIÓN | E38: ALIMENTARSE | F38: ALIMENTACIÓN
C39: TSER | D39: DEFINICIÓN | E39: DEFINIR PROCESOS Y CRITERIOS INGENIERILES | F39: DEFINICIÓN
C40: SMART | D40: REVISIÓN PLANIFICACIÓN DE PIÑAS | F40: PLANIFICACIÓN
C41: SMART | D41: REVISIÓN PROGRAMACIÓN PLÁTANO | F41: PLANIFICACIÓN
C42: SMART | D42: REVISIÓN PROGRAMACIÓN CACAO | F42: PLANIFICACIÓN
C43: SMART | D43: PROGRAMACIÓN DE TRANSPORTE | E43: CUADRE DE VEHÍCULOS EN BASE A LOS CORTES QUE ESTÁN PROGRAMADOS. REVISIÓN SOLICITUD DE OMARSA REVISIÓN LISTADO DE PROVEEDORES DE TRANSPORTE. REVISIÓN ASIGNACIÓN DE CHOFERES TANTO PROVEEDORES DE TRANSPORTE COMO PROVEEDORES PROPIOS. GENERACIÓN DE PLANIFICACIÓN DE TRANSPORTE DEL CORTE DEL MARTES. PLANIFICACIÓN DE BANANO REVISA EN FTL Y SE LO UBICA EN LA BASE DE TRANSPORTE. | F43: RECEPCIÓN DE SOLICITUD DE TRANSPORTE
C44: SMART | D44: REVISIÓN KILOMETRAJE INICIO DE SEMANA | E44: REVISIÓN KILOMETRAJE DE LOS VEHÍCULOS DE SMART DE LA SEMANA ANTERIOR. | F44: CONSOLIDACIÓN
C45: SMART | D45: REVISIÓN PROGRAMACIÓN OPERACIONES | E45: REVISIÓN DE CAMBIOS. LISTA DE ACOPIOS. | F45: PLANIFICACIÓN
C46: SMART | D46: REVISIÓN PROGRAMACIÓN BANANO | F46: PLANIFICACIÓN
C47: SMART | D47: PROGRAMACIÓN DE OLAM | F47: PLANIFICACIÓN
C48: SMART | D48: ELABORACIÓN KILOMETRAJE FINALIZACIÓN | F48: CONSOLIDACIÓN
C49: SMART | D49: RENOVACIÓN DE DOCUMENTOS DE VEHÍCULOS EN PUERTOS | F49: CONTROL DOCUMENTAL DE LA FLOTA
C50: SMART | D50: REVISIÓN PROGRAMACIÓN EN FTL | E50: REVISAR SI HAY ALGÚN CAMBIO QUE HAYA HECHO TROPICAL. TODO CAMBIO DEBE REPORTARSE EN EL GRUPO DE FALLAS VÍA WHATSAPP. | F50: PLANIFICACIÓN
C51: SMART | D51: AJUSTE DE PROGRAMACIÓN DE DESPACHO | E51: CON RESPECTO AL DÍA ANTERIOR. | F51: PLANIFICACIÓN
C52: SMART | D52: PROGRAMACIÓN DE PLÁTANO, PIÑAS Y CACAO | F52: PLANIFICACIÓN
C53: SMART | D53: HORÓMETROS DE VIAJE CON GENERADOR | F53: CONTROL DEL CUMPLIMIENTO DE LA CADENA DE FRÍO
C54: SMART | D54: REVISIÓN VEHÍCULOS LOGÍSTICA | F54: GESTIÓN DE LA PLANIFICACIÓN
C55: SMART | D55: REVISIÓN DE FACTURAS DE GENERADORES | F55: CONTROL DOCUMENTAL DE PROVEDURÍA
C56: TSER | D56: Control y validación de reporte de transporte de contenedor | E56: Realizar la verificación y validación del reporte de viajes elaborado por el responsable del área (Oscar Ortega), asegurando que las tarifas se encuentren correctamente actualizadas conforme a lo establecido en el tarifario. Además, detallar los códigos de artículos correspondientes para el control y registro de las facturas emitidas por cada transportista. Asignar los activos | F56: PLANIFICACIÓN
C57: TSER | D57: Envío de reporte de transporte para facturación | E57: Realizar el envío del reporte de viajes al área de Contabilidad TFE, con el fin de que se efectúe la correspondiente facturación. | F57: FACTURACIÓN
C58: TSER | D58: Control y seguimiento de soportes y escaneos documentales | E58: Realizar el control y seguimiento de los soportes físicos y escaneados de los viajes, en coordinación con los responsables de garita, para el envío al cliente OLAM. la validación documental final es efectuada por melanie villa. | F58: GESTIÓN DOCUMENTAL
C59: TSER | D59: Control y seguimiento de soportes pendientes de reportes de viajes | E59: Realizar el control y seguimiento de los soportes pendientes de recepción, coordinar con los transportistas la remisión de los documentos faltantes. En los casos en que no se obtenga respuesta por parte del transportista, remitir el archivo actualizado de soportes pendientes a oscar ortega para su conocimiento y seguimiento. La validación documental final es realizada por melanie villa. | F59: GESTIÓN DOCUMENTAL
C60: TSER | D60: Creación de proveedores y artículos en Sap | E60: Realizar la creación de nuevos proveedores, creación de nuevos artículos solicitados por los departamentos establecidos. | F60: CREACIÓN SAP
C61: TSER | D61: Control y seguimiento de caja chica | E61: Realizar el control y seguimiento de los registros de caja chica en el sistema sap, verificando que coincidan con los documentos físicos de respaldo y archivar de manera ordenada. | F61: CAJA CHICA
C62: TSER | D62: Verificación de anulación de retenciones | E62: Verificar la correcta anulación de las retenciones registradas en sap, posterior a la anulación en el sistema, se efectúe la solicitud correspondiente en el portal del sri, garantizando la coherencia entre ambas plataformas y la trazabilidad del proceso contable. | F62: RETENCIONES
C63: TSER | D63: Elaboración y envío de reporte de ventas de empresas relacionadas | E63: Elaborar y consolidar el reporte de ventas correspondiente a las empresas relacionadas, clasificando la información por tipo de carga (banano y plátano). | F63: GESTIÓN DOCUMENTAL
C64: TSER | D64: Control y actualización del registro de transportistas tercerizados | E64: Elaborar, actualizar y gestionar el listado y la documentación de los conductores y transportistas tercerizados, verificando el cumplimiento de los requisitos y estándares establecidos por la auditoría basc. asegurar que toda la información se mantenga vigente. | F64: PLANIFICACIÓN
C65: TSER | D65: Control y validación de liquidación de Grupo Noboa | E65: Realizar y enviar de detalle de valores semanales a los que aplica, facturación de Grupo Noboa en SAP, envío de facturas por correo electronico | F65: LIQUIDACIÓN
C66: TSER | D66: Gestionar y validar las devoluciones a productores | E66: Devoluciones a productores, generación de notas de crédito, entre varios casos | F66: GESTIÓN DOCUMENTAL
C67: TSER | D67: Emisión de Facturas de Reembolso | E67: Facturas de reembolso mensuales (Cedillo, Farletza) | F67: REEMBOLSO
... C137: TSER | D137: SOLICITUD DE DEVOLUCIONES DE IMPUESTOS DE TSER | E137: SCANNER DE LAS DEVOLUCIONES DE IVA EXPORTADOR DE TSER. | F137: DEVOLUCIONES IVA
C138: TSER | D138: SEGUIMIENTO DEL CIERRE DE MES | F138: ANÁLISIS Y CRITERIO INGENIERIL
C139: TSER | D139: REUNIÓN - CÉSAR GUATO | F139: ANÁLISIS Y CRITERIO INGENIERIL
C140: TSER | D140: INGRESO DE PROFORMAS ( CMA - KING OCEAN - ONE SEABOARD ) | E140: Se ingresa a las paginas web de la navieras asigandas y se coloca toda la informacion que van a llevar los contenedores de manera correcta , se ingresa las proformas dentro plazos documentales que cada naviera. | F140: PROFORMAS
C141: TSER | D141: OK DE BLS FINALES NAVIERAS ( CMA - KING OCEAN - ONE SEABOARD ) | E141: Corregir la informacion que nos envia la naviera de los BLS finales, tomando la informacion de los cierres de contenedores semanales (FTL) | F141: GESTIÓN DOCUMENTAL
C142: TSER | D142: ELABORACION DE PLANES DE EMBARQUES DEFINTIVOS ( BANANOS ) | E142: Se realiza un reporte de toda la exportacion de Banano para la respectiva declaracion final ante el MAG. | F142: GESTIÓN DOCUMENTAL
C143: TSER | D143: CIERRE DE EXPORTACIONES ( CMA - KING OCEAN ONE - SEABOARD ) hasta 15 dias posterior al manifiesto de navieras asignadas. | E143: Se declara ante la SENAE la informacion final que se obtiene cuando la semana de exportacion culmina debe estar lista la informacion ,factura , Cierres de planes de embarque para poder declara la informacion correcta de lo que se exporto. | F143: GESTIÓN DOCUMENTAL
C144: TSER | D144: INGRESO DE FACTURAS (PROVEEDORES COMEX) TSER | E144: Cada inicio de semana llegan las facturas sean por Navieras - Depositos - Retiros - Inspeciones, confimamos que todas las facturas que nos lleguen esten facturadas con su razon social correcta y valores correctos. Esperamos el detalle que envia el area de contabilidad para confirmar que todo se ingrese de manera correcta y dentro de los plazos del area financiera. | F144: FACTURACIÓN
C145: TSER | D145: APERTURAS DE DAES NAVIERAS ASIGNADAS | E145: Tomamos la informacion de los pedidos semanales y confirmamos con la programacion la cantidad de contendores que vamos a exportar esa semana para asi poder generar las DAES | F145: GESTIÓN DOCUMENTAL
C146: TSER | D146: APERTURAS DE DOCUMENTO DE CONTROL PREVIO / DCP ( CMA - KING OCEAN - ONE SEABOARD ) | E146: Revisamos la programacion semanal de los pedidos y confirmamos que se realizra, para asi genera el documento de control previo (DCP) para la generacion de DAES. | F146: GESTIÓN DOCUMENTAL
C147: TSER | D147: ELABORACION DE ISF (Naviera USA ) | E147: Cuando hayan concluido con las programaciones de cada naviera, esta informacion se envia por medio de correo al Notify, donde se ingresa toda la informacion referente al embarque de acuerdo con los plazos documentales se realiza la generacion de ISF en plantillas de Excel. | F147: GESTIÓN DOCUMENTAL
C148: TSER | D148: INGRESOS EN EL SISTEMA DE VERIFICACION (VGM ) | E148: Ingresamos la informacion en la pagina de la naviera ( Booking - Contenedor) donde colocamos el peso de cada contendor para asi confirmar que los embarque no presenten problemas en cuanto al peso de la nave. | F148: VERIFICACIÓN
C149: TSER | D149: DECLARACION DE CARTAR DE TEMPERATURA NAVIERAS ASIGNADAS | E149: Se ingresa a las paginas web de la navieras o se realiza plantillas en Excel donde se coloca toda la informacion y las especificaciones de las temperatura que solicita cada cliente para cada producto. | F149: DECLARACIONES
C150: TSER | D150: LIBERACION DE BLS SWB (Contenedores) POR PAGOS PENDIENTES estados de cuenta | E150: Se solicita a la naviera liberacion por correo despues de cancelar los valores a pagar por las exportaciones y asi solicitar el envio de los BLS (SWB) despues que las naves zarparan y se exportaran todos los contenedores. | F150: GESTIÓN NAVIERA
C151: TSER | D151: DIGITALIZACIONES ( CMA - KING OCEAN ONE - SEABOARD ) | E151: Una vez regularizada las DAES de las navieras asignadas se recopila la siguentes informacion: DAE regularizada, factura, BLS , capture del estado regularizada en el ECUAPASS , se realiza 1 PDF con esos 4 documentos y se los coloca en la red. | F151: DIGITALIZACIONES
... C156: TSER | D156: AFOROS INSTRUSIVOS ( DOCUMENTOS - SEGUIMIENTO ) NAVIERAS ASIGNADAS | E156: Se realiza la respectiva correcion a la Dae (Senae) y se procede con el envio de la documentacion al area de seguridad, donde asistiran a la inspecion intrusiva el cual debemos estar pendientes y dar seguimiento a la dae hasta que esta misma cuente con salida autorizada. | F156: VERIFICACIÓN
C157: TSER | D157: DISTRIBUCIÓN DE WALMART FOB | F157: GESTIÓN DOCUMENTAL
C158: TSER | D158: DISTRIBUCIÓN DE SEABOARD | F158: GESTIÓN DOCUMENTAL
C159: TSER | D159: IFS NAVIERAS ASIGNADAS | F159: GESTIÓN DOCUMENTAL
C160: TSER | D160: CT NAVIERAS ASIGNADAS | F160: VERIFICACIÓN
C161: TSER | D161: REDUCCIÓN DE CONTENEDORES NAVIERAS ASIGNADAS | F161: GESTIÓN NAVIERA
C162: TSER | D162: SOPORTE INTRADEPARTAMENTAL | E162: SOPORTE EN DOCUMENTOS FITOSANITARIOS | F162: SOPORTE
C163: TSER | D163: CIERRE DOCUMENTACIÓN DCP | F163: GESTIÓN DOCUMENTAL
C164: TSER | D164: Reportar siniestros property | E164: Reportar y documentar siniestros en caso que sucedan en los diferentes ramos Property | F164: SINIESTROS
C165: TSER | D165: Elaborar reporte de siniestro transporte terrestre | E165: Reportar y documentar siniestro ocurrido, inspeccionar carga y posteriormente gestionar venta salvataje | F165: SINIESTROS
C166: TSER | D166: Elaborar reporte de siniestro transporte maritimo | E166: Reportar y documentar siniestro ocurrido en cargas exportadas | F166: SINIESTROS
C167: TSER | D167: Actualizar base de reclamos de clientes | E167: Actualizar la base de reclamos de clientes por aquellos casos reportados al seguro | F167: REPORTERIA
C168: TSER | D168: Registrar pagos de indemnizaciones del seguro | E168: Registrar en SAP los pagos recibidos por indemnizaciones de los casos reportados | F168: REPORTERIA
C169: TSER | D169: Realizar conciliación bancaria | E169: Conciliar información entre los estados de cuentas de los bancos | F169: CONCIALICIÓN
C170: TSER | D170: Compensar anticipos con facturas | E170: Realizar compensación de pagos con facturas para posteriormente crear reporte de CXP | F170: REPORTERIA
C171: TSER | D171: Descargar estados de cuentas bancarios | E171: Descargar y guardar estados de cuentas bancarios al finalizar el mes en formato PDF y Excel | F171: REPORTERIA
C172: TSER | D172: Realizar pagos de nómina | E172: Realizar pagos de eventuales, servicios prestados y recorridos | F172: NÓMINA
C173: TSER | D173: Registro de pagos en MLC, TFE, TSER | E173: Registrar los pagos realizados durante la semana | F173: PAGOS
C174: TSER | D174: Realizar pago de proveedores luego de haberse realizado el fondeo | E174: Seleccionar en SAP las facturas que serán pagadas acorde lo planificado en el fondeo semanal | F174: PAGOS
C175: TSER | D175: Realizar pago de proveedores de supply a través de Cadena de Valor/Banco Pichincha | E175: Seleccionar en SAP las facturas que serán pagadas acorde lo planificado en el fondeo semanal | F175: PAGOS
... C209: TSER | D209: Reporte de siniestro Coface | E209: Reportar y documentar el caso en la plataforma coface. | F209: SINIESTRO SEGURO

Sheet CONTENIDO DE TRABAJO
C2: EXP GROUP LLC | D2: SEABORAD | G2: WALMART CHILE | H2: KN | I2: EXP GROUP LLC | J2: SEABORAD
C3: 1 PRODUCTO | D3: 1 PRODUCTO | E3: 1 PRODUCTO | F3: 2 PRODUCTOS | G3: 1 PRODUCTO | I3: 1 PRODUCTO
B4: ACTIVIDAD | C4: TIEMPO 1 | D4: TIEMPO 2 | E4: TIEMPO 3 | F4: TIEMPO 4 | G4: TIEMPO 5
B5: FACTURACIÓN CIF BANANO A CLIENTES EN MULTINATIONAL | C5: 6.14.28 | D5: 4.34.27 | E5: 2.58.38 | F5: 4.51.36 | P5: Detalle de trámites | Q5: n factura, puerto destino, n contenedores, n tramite
C6: 1.35.65 | E6: 0.56.35 | F6: 1.39.85 | P6: BL | Q6: peso, n contenedor, nombre producto, n cajas, puerto origen, destino
C7: 0.18.68 | F7: 0.23.02 | P7: Precio | Q7: n articulo, nombre producto, precio
B8: FACTURACIÓN CIF PLÁTANO A CLIENTES EN MULTINATIONAL | G8: 5.58.13 | I8: 3.11.44 | P8: Consolidación | Q8: todo lo anterior
G9: 0.49.44 | I9: 2.03.83
G10: 0.38.26
